Workbook
Name Global_Discount_Cap: 'What-If Analysis'!$B$4
Name Label: 'What-If Analysis'!$B$3
Name Quantity_Uplift: 'What-If Analysis'!$B$6
Name Slicer_Channel: #N/A
Name Slicer_Country: #N/A
Name Slicer_Months: #N/A
Name Slicer_ProductCategory1: #N/A
Name Slicer_Region1: #N/A
Name Slicer_Salesperson: #N/A
Name Unit_Cost_Inflation: 'What-If Analysis'!$B$5

Sheet Raw Data
A1: OrderID | B1: OrderDate | C1: RequiredDate | D1: Region | E1: Country | F1: City | G1: CustomerSegment | H1: Channel | I1: Salesperson | J1: ProductCategory | K1: SKU | L1: UnitCost | M1: UnitPrice | N1: DiscountPct | O1: Quantity
A2: ORD-2024-275203 | B2: 45362 | C2: 45388 | D2: Africa | E2: Kenya | F2: Kisumu | G2: Corporate | H2: Retail | I2: C. Otieno | J2: Components | K2: CMP-8270 | L2: 279.24 | M2: 608.9 | N2: 0.112 | O2: 9
A3: ORD-2024-358795 | B3: 45588 | C3: 45587 | D3: Africa | E3: Nigeria | F3: Port Harcourt | G3: Education | H3: Online | I3: J. Njeri | J3: Printers | K3: PRN-9322 | L3: 1084.39 | M3: 759.33 | N3: 0.237 | O3: 31
A4: ORD-2023-373538 | B4: 44985 | C4: 45010 | D4: Africa | E4: Kenya | F4: Nairobi | G4: Corporate | H4: Retail | I4: I. Johnson | J4: Networking | K4: NET-9666 | L4: 1460.76 | M4: -30.66 | N4: 0.131 | O4: 12
A5: ORD-2025-168148 | B5: 45745 | C5: 45749 | D5: Africa | E5: Nigeria | F5: Lagos | G5: Non-Profit | H5: Marketplace | I5: G. Dubois | J5: Phones | K5: PHN-4556 | L5: 259.93 | M5: 255.94 | N5: 0.072 | O5: 22
A6: ORD-2023-824839 | B6: 45266 | C6: 45291 | D6: Asia | E6: Japan | F6: Osaka | G6: Consumer | H6: Retail | I6: L. Okafor | J6: Printers | K6: PRN-8041 | L6: 663.03 | M6: 813.51 | N6: 0.102 | O6: 15
A7: ORD-2023-723587 | B7: 44928 | C7: 44931 | D7: Americas | E7: Canada | F7: Toronto | G7: Corporate | H7: Distributor | I7: B. Chen | J7: Laptops | K7: LAP-8555 | L7: 315.87 | M7: 591.68 | N7: 0 | O7: 7
A8: ORD-2024-336584 | B8: 45653 | C8: 45671 | D8: Asia | E8: India | F8: Bengaluru | G8: Small Business | H8: Marketplace | I8: E. Garcia | J8: Monitors | K8: MON-8629 | L8: 586.07 | M8: 845.97 | N8: 0.147 | O8: 4
A9: ORD-2023-112666 | B9: 44941 | C9: 44939 | D9: Africa | E9: Nigeria | F9: Abuja | G9: Education | H9: Online | I9: O. Wang | J9: Printers | K9: PRN-6276 | L9: 28.38 | M9: 47.22 | N9: 0.194 | O9: 18
A10: ORD-2024-589570 | B10: 45416 | C10: 45441 | D10: Africa | E10: Nigeria | F10: Abuja | G10: Non-Profit | H10: Marketplace | I10: O. Wang | J10: Monitors | K10: MON-6892 | L10: 1295.34 | M10: 2530.81 | N10: 0.031 | O10: 6
A11: ORD-2025-997421 | B11: 45798 | C11: 45817 | D11: Americas | E11: Brazil | F11: São Paulo | G11: Non-Profit | H11: Online | I11: A. Patel | J11: Components | K11: CMP-3731 | L11: 1331.38 | M11: 2309.56 | N11: 0.149 | O11: 31
A12: ORD-2024-210687 | B12: 45319 | C12: 45331 | D12: Europe | E12: Germany | F12: Berlin | G12: Corporate | H12: Online | I12: G. Dubois | J12: Accessories | K12: ACC-7938 | L12: 644.17 | M12: 700.12 | N12: 0.006 | O12: 23
A13: ORD-2025-515515 | B13: 45660 | C13: 45680 | D13: Asia | E13: Japan | F13: Osaka | G13: Corporate | H13: Distributor | I13: F. Müller | J13: Phones | K13: PHN-7019 | L13: 908.6 | M13: 691.37 | N13: 0.25 | O13: 20
... A34: ORD-2025-474710 | B34: 45862 | C34: 45875 | D34: Africa | E34: South Africa | F34: Johannesburg | G34: Education | H34: Marketplace | I34: D. Smith | J34: Networking | K34: NET-7966 | L34: 1463.9 | M34: 2633.02 | N34: 0.084 | O34: 4
A35: ORD-2024-629525 | B35: 45400 | C35: 45420 | D35: Europe | E35: United Kingdom | F35: London | G35: Non-Profit | I35: D. Smith | J35: Laptops | K35: LAP-9932 | L35: 645.33 | M35: 1321.85 | N35: 0 | O35: 10
A36: ORD-2024-167215 | B36: 45527 | C36: 45525 | D36: Africa | E36: South Africa | F36: Johannesburg | G36: Education | H36: Retail | I36: E. Garcia | J36: Components | K36: CMP-1559 | L36: 1432.52 | M36: 3036.87 | N36: 0 | O36: 9
A37: ORD-2023-864121 | B37: 45012 | C37: 45038 | D37: Asia | E37: India | F37: Delhi | G37: Non-Profit | H37: Marketplace | I37: J. Njeri | J37: Printers | K37: PRN-4506 | L37: 178.53 | M37: 199.37 | N37: 0.101 | O37: 37
A38: ORD-2024-692673 | B38: 45358 | C38: 45376 | D38: Europe | E38: Germany | F38: Munich | G38: Corporate | H38: Online | I38: B. Chen | J38: Components | K38: CMP-7617 | L38: 712.84 | M38: 927.51 | N38: 0.243 | O38: 27
A39: ORD-2025-718992 | B39: 45832 | C39: 45848 | D39: Asia | E39: China | F39: Shanghai | G39: Enterprise | H39: Direct | I39: N. Brown | J39: Components | K39: CMP-8390 | L39: 757.19 | M39: 1735.41 | N39: 0.136 | O39: 8
A40: ORD-2024-599522 | B40: 45401 | C40: 45418 | D40: Africa | E40: Nigeria | F40: Port Harcourt | G40: Non-Profit | H40: Online | I40: A. Patel | J40: Printers | K40: PRN-7303 | L40: 865.33 | M40: 1395.64 | N40: 0.175 | O40: 13
A41: ORD-2023-651638 | B41: 45094 | C41: 45101 | D41: Americas | E41: USA | F41: San Francisco | G41: Corporate | H41: Retail | I41: I. Johnson | J41: Printers | K41: PRN-6536 | L41: 313.99 | M41: 454.42 | N41: 0.129 | O41: 9
A42: ORD-2024-635626 | B42: 45531 | C42: 45554 | D42: Europe | E42: Germany | F42: Berlin | G42: Small Business | H42: Direct | I42: D. Smith | J42: Monitors | K42: MON-9967 | L42: 1024.01 | M42: 1580.97 | N42: 0.037 | O42: 27
A43: ORD-2024-296582 | B43: 45302 | C43: 45324 | D43: Africa | E43: South Africa | F43: Durban | G43: Consumer | H43: Online | I43: K. Singh | J43: Networking | K43: NET-1412 | L43: 1206.2 | M43: 1759.79 | N43: 0 | O43: 6
A44: ORD-2024-998320 | B44: 45590 | C44: 45610 | D44: Africa | E44: Kenya | F44: Mombasa | G44: Corporate | H44: Direct | I44: H. Kim | J44: Printers | K44: PRN-3143 | L44: 1396.48 | M44: 3204.5 | N44: 0.318 | O44: 14
A45: ORD-2025-820255 | B45: 45806 | C45: 45828 | D45: Europe | E45: Germany | F45: Berlin | G45: Corporate | H45: Direct | I45: A. Patel | J45: Printers | K45: PRN-9787 | L45: 483.47 | M45: 1135.43 | N45: 0.146 | O45: 11
A46: ORD-2024-389336 | B46: 45432 | C46: 45445 | D46: Americas | E46: Canada | F46: Vancouver | G46: Enterprise | H46: Marketplace | I46: K. Singh | J46: Components | K46: CMP-5946 | L46: 675.43 | M46: 996.36 | N46: 0.182 | O46: 22
A47: ORD-2023-308124 | B47: 45035 | C47: 45046 | D47: Asia | E47: India | F47: Delhi | G47: Small Business | H47: Retail | I47: A. Patel | J47: Networking | K47: NET-2062 | L47: 826.55 | M47: 1397.05 | N47: 0.169 | O47: 28
... A77: ORD-2023-722117 | B77: 45187 | C77: 45207 | D77: Asia | E77: India | F77: Delhi | G77: Small Business | H77: Direct | I77: B. Chen | J77: Components | K77: CMP-1009 | L77: 825.64 | M77: 1108.43 | N77: 0.114 | O77: 7
A78: ORD-2024-446699 | B78: 45532 | C78: 45560 | D78: Americas | E78: Brazil | F78: Rio de Janeiro | G78: Non-Profit | H78: Online | J78: Accessories | K78: ACC-4490 | L78: 1394.65 | M78: 3144.1 | N78: 0.134 | O78: 13
A79: ORD-2024-451005 | B79: 45473 | C79: 45471 | D79: Americas | E79: Brazil | F79: Rio de Janeiro | G79: Small Business | H79: Direct | I79: L. Okafor | J79: Accessories | K79: ACC-9162 | L79: 1112.98 | M79: 2095.73 | N79: 0.072 | O79: 17
A80: ORD-2023-290279 | B80: 45091 | C80: 45093 | D80: Europe | E80: United Kingdom | F80: Manchester | G80: Non-Profit | H80: Direct | I80: K. Singh | J80: Components | K80: CMP-5820 | L80: 357.36 | M80: 703.62 | N80: 0.257 | O80: 20
A81: ORD-2024-192263 | B81: 45617 | C81: 45647 | D81: Europe | E81: France | F81: Marseille | G81: Small Business | H81: Direct | I81: I. Johnson | J81: Monitors | K81: MON-7943 | L81: 1122.68 | M81: 1997.19 | N81: 0.186 | O81: 3
A82: ORD-2023-159379 | B82: 44965 | C82: 44968 | D82: Africa | E82: South Africa | F82: Cape Town | G82: Corporate | H82: Direct | I82: M. Rossi | J82: Networking | K82: NET-5018 | L82: 1410.05 | M82: 2763.95 | N82: 0.161 | O82: 26
A83: ORD-2023-343322 | B83: 45157 | C83: 45181 | D83: Americas | E83: Canada | F83: Vancouver | G83: Enterprise | H83: Retail | I83: I. Johnson | J83: Printers | K83: PRN-9669 | L83: 1183.95 | M83: 1503.53 | N83: 0.241 | O83: 16
A84: ORD-2025-114382 | B84: 45791 | C84: 45801 | D84: Europe | E84: France | F84: Paris | G84: Small Business | H84: Marketplace | I84: K. Singh | J84: Components | K84: CMP-2865 | L84: 170.39 | M84: 388.04 | N84: 0.084 | O84: 15
A85: ORD-2025-488349 | B85: 45770 | C85: 45769 | D85: Americas | E85: USA | F85: San Francisco | G85: Non-Profit | H85: Distributor | I85: D. Smith | J85: Monitors | K85: MON-3371 | L85: 23.24 | M85: 44.57 | N85: 0.215 | O85: 15
A86: ORD-2025-330203 | B86: 45741 | C86: 45764 | D86: Europe | E86: United Kingdom | F86: London | G86: Consumer | H86: Retail | I86: H. Kim | J86: Networking | K86: NET-7166 | L86: 1421.19 | M86: 1808.26 | N86: 0.104 | O86: 13
A87: ORD-2023-841426 | B87: 45282 | C87: 45283 | D87: Africa | E87: South Africa | F87: Cape Town | G87: Non-Profit | H87: Marketplace | I87: D. Smith | J87: Components | K87: CMP-4531 | L87: 1186.18 | M87: 1285.09 | N87: 0.07 | O87: 11
A88: ORD-2024-594592 | B88: 45388 | C88: 45407 | D88: Asia | E88: China | F88: Shanghai | G88: Corporate | H88: Retail | I88: K. Singh | J88: Components | K88: CMP-8196 | L88: 1366.48 | M88: 1678.14 | N88: 0.154 | O88: 10
A89: ORD-2025-863978 | B89: 45876 | C89: 45888 | D89: Africa | E89: Kenya | F89: Nakuru | G89: Corporate | I89: M. Rossi | J89: Components | K89: CMP-2854 | L89: 601.51 | M89: 679.35 | N89: 0.188 | O89: 3
A90: ORD-2024-604471 | B90: 45312 | C90: 45316 | D90: Asia | E90: India | F90: Delhi | G90: Consumer | H90: Direct | I90: C. Otieno | J90: Monitors | K90: MON-8973 | L90: 523.7 | M90: 1109.92 | N90: 0.03 | O90: 11
A91: ORD-2023-258768 | B91: 45106 | C91: 45109 | D91: Asia | E91: Japan | F91: Nagoya | G91: Education | H91: Marketplace | I91: F. Müller | J91: Monitors | K91: MON-2990 | L91: 55.65 | M91: 83.57 | N91: 0.066 | O91: 8
A92: ORD-2025-626047 | B92: 45775 | C92: 45792 | D92: Asia | E92: Japan | F92: Nagoya | G92: Education | H92: Direct | I92: N. Brown | J92: Networking | K92: NET-1966 | L92: 691.19 | M92: 1284.3 | N92: 0.074 | O92: 7
A93: ORD-2025-526752 | B93: 45817 | C93: 45833 | D93: Asia | E93: India | F93: Hyderabad | G93: Enterprise | H93: Distributor | I93: M. Rossi | J93: Phones | K93: PHN-3482 | L93: 527.33 | M93: 911.72 | N93: 0.144 | O93: 25
A94: ORD-2023-374486 | B94: 45101 | C94: 45100 | D94: Americas | E94: Brazil | F94: Rio de Janeiro | G94: Non-Profit | H94: Retail | I94: E. Garcia | J94: Printers | K94: PRN-6490 | L94: 804.01 | M94: 1405.07 | N94: 0.096 | O94: 8
A95: ORD-2024-997336 | B95: 45569 | C95: 45598 | D95: Africa | E95: Nigeria | F95: Abuja | G95: Corporate | H95: Distributor | I95: F. Müller | J95: Accessories | K95: ACC-9038 | L95: 412.09 | M95: 968.94 | N95: 0.099 | O95: 23
A96: ORD-2025-725646 | B96: 45910 | C96: 45930 | D96: Africa | E96: Kenya | F96: Mombasa | G96: Corporate | H96: Direct | I96: L. Okafor | J96: Phones | K96: PHN-6954 | L96: 1009.48 | M96: 1088.81 | N96: 0.16 | O96: 6
A97: ORD-2023-868734 | B97: 45022 | C97: 45043 | D97: Europe | E97: United Kingdom | F97: Manchester | G97: Enterprise | H97: Distributor | I97: I. Johnson | J97: Printers | K97: PRN-8970 | L97: 1084.79 | M97: 2484.99 | N97: 0.034 | O97: 18
A98: ORD-2025-262491 | B98: 45870 | C98: 45885 | D98: Asia | E98: India | G98: Enterprise | H98: Direct | I98: O. Wang | J98: Monitors | K98: MON-1822 | L98: 24.44 | M98: 28.69 | N98: 0.146 | O98: 6
A99: ORD-2024-638884 | B99: 45440 | C99: 45438 | D99: Africa | E99: Nigeria | F99: Abuja | G99: Enterprise | H99: Online | I99: F. Müller | J99: Accessories | K99: ACC-5177 | L99: 1227.08 | M99: 1896.62 | N99: 0 | O99: 18
A100: ORD-2025-541501 | B100: 45860 | C100: 45887 | D100: Asia | E100: China | F100: Shenzhen | G100: Non-Profit | H100: Marketplace | I100: M. Rossi | J100: Networking | K100: NET-1804 | L100: 547.32 | M100: 419.17 | N100: 0.092 | O100: 14
A101: ORD-2023-422918 | B101: 44985 | C101: 45005 | D101: Europe | E101: Germany | F101: Berlin | G101: Small Business | H101: Direct | I101: H. Kim | J101: Laptops | K101: LAP-3679 | L101: 1200.78 | M101: 2001.17 | N101: 0.292 | O101: 18
A102: ORD-2025-328504 | B102: 45684 | C102: 45703 | D102: Asia | E102: China | F102: Shenzhen | G102: Non-Profit | H102: Direct | I102: L. Okafor | J102: Phones | K102: PHN-8368 | L102: 1253.22 | M102: 3104.71 | N102: 0 | O102: 17
A103: ORD-2024-851883 | B103: 45304 | C103: 45313 | D103: Asia | E103: India | F103: Mumbai | G103: Enterprise | H103: Marketplace | I103: J. Njeri | J103: Components | K103: CMP-8141 | L103: 313.6 | M103: 334.28 | N103: 0.14 | O103: 22
A104: ORD-2025-662997 | B104: 45747 | C104: 45751 | D104: Africa | E104: Kenya | F104: Nakuru | G104: Corporate | H104: Direct | I104: C. Otieno | J104: Laptops | K104: LAP-7136 | L104: 862.08 | M104: 1952.83 | N104: 0 | O104: 7
A105: ORD-2024-478165 | B105: 45631 | C105: 45654 | D105: Americas | E105: Canada | F105: Vancouver | G105: Corporate | H105: Direct | I105: F. Müller | J105: Accessories | K105: ACC-2386 | L105: 107.03 | M105: 242.29 | N105: 0.18 | O105: 30
A106: ORD-2024-771210 | B106: 45549 | C106: 45570 | D106: Asia | E106: China | F106: Shanghai | G106: Small Business | H106: Online | I106: H. Kim | J106: Laptops | K106: LAP-5150 | L106: 1405.56 | M106: 2968.87 | N106: 0.169 | O106: 5
A107: ORD-2024-155337 | B107: 45433 | C107: 45439 | D107: Africa | E107: South Africa | F107: Johannesburg | G107: Non-Profit | H107: Online | I107: M. Rossi | J107: Components | K107: CMP-8101 | L107: 1157.51 | M107: 1394.3 | N107: 0.278 | O107: 12
A108: ORD-2023-251563 | B108: 45057 | C108: 45084 | D108: Africa | E108: Kenya | F108: Mombasa | G108: Corporate | H108: Online | I108: J. Njeri | J108: Phones | K108: PHN-8970 | L108: 12.85 | M108: 15.41 | N108: 0.137 | O108: 39
A109: ORD-2024-286833 | B109: 45518 | C109: 45539 | D109: Europe | E109: United Kingdom | F109: Manchester | G109: Non-Profit | H109: Online | I109: J. Njeri | J109: Phones | K109: PHN-2341 | L109: 1138.8 | M109: 2250.81 | N109: 0.123 | O109: 12
A110: ORD-2024-792558 | B110: 45581 | C110: 45604 | D110: Asia | E110: Japan | F110: Osaka | G110: Small Business | H110: Retail | I110: J. Njeri | J110: Networking | K110: NET-6387 | L110: 82.14 | M110: 166.04 | N110: 0 | O110: 10
... A121: ORD-2025-956101 | B121: 45847 | C121: 45856 | D121: Americas | E121: Canada | F121: Vancouver | G121: Education | H121: Distributor | I121: I. Johnson | J121: Laptops | K121: LAP-2218 | L121: 57.96 | M121: 88.51 | N121: 0.043 | O121: 7
A122: ORD-2025-184082 | B122: 45827 | C122: 45850 | D122: Europe | E122: United Kingdom | G122: Non-Profit | H122: Direct | J122: Networking | K122: NET-6370 | L122: 801.24 | M122: 1959.09 | N122: 0.123 | O122: 23
A123: ORD-2023-576840 | B123: 45249 | C123: 45273 | D123: Europe | E123: France | F123: Lyon | G123: Non-Profit | H123: Direct | I123: H. Kim | J123: Monitors | K123: MON-3745 | L123: 1297.42 | M123: 2742.97 | N123: 0.069 | O123: 9
A124: ORD-2023-178249 | B124: 45289 | C124: 45311 | D124: Africa | E124: Kenya | F124: Kisumu | G124: Corporate | H124: Direct | I124: L. Okafor | J124: Phones | K124: PHN-7924 | L124: 1395.49 | M124: 1679.42 | N124: 0.203 | O124: 12
A125: ORD-2024-588972 | B125: 45598 | C125: 45625 | D125: Americas | E125: Brazil | F125: Brasília | G125: Small Business | H125: Direct | I125: I. Johnson | J125: Networking | K125: NET-8561 | L125: 1363.51 | M125: 1433.9 | N125: 0.057 | O125: 8
A126: ORD-2023-603238 | B126: 45159 | C126: 45173 | D126: Americas | E126: Canada | F126: Montreal | G126: Education | H126: Distributor | I126: F. Müller | J126: Components | K126: CMP-2136 | L126: 178.19 | M126: 284.43 | N126: 0.089 | O126: 8
A127: ORD-2023-883066 | B127: 45150 | C127: 45175 | D127: Asia | E127: China | F127: Shanghai | G127: Small Business | H127: Retail | I127: B. Chen | J127: Components | K127: CMP-6352 | L127: 950.77 | M127: 694.78 | N127: 0.084 | O127: 14
A128: ORD-2024-584090 | B128: 45450 | C128: 45469 | D128: Europe | E128: Germany | F128: Berlin | G128: Non-Profit | H128: Marketplace | I128: M. Rossi | J128: Components | K128: CMP-2040 | L128: 1064.32 | M128: 1848.39 | N128: 0.073 | O128: 38
A129: ORD-2025-537785 | B129: 45874 | C129: 45883 | D129: Europe | E129: United Kingdom | F129: London | G129: Non-Profit | H129: Direct | I129: E. Garcia | J129: Components | K129: CMP-6346 | L129: 41.76 | M129: 45.19 | N129: 0.179 | O129: 23
A130: ORD-2024-605518 | B130: 45442 | C130: 45456 | D130: Americas | E130: USA | F130: San Francisco | G130: Small Business | H130: Retail | I130: F. Müller | J130: Phones | K130: PHN-4356 | L130: 157.78 | M130: 361.1 | N130: 0.187 | O130: 9
A131: ORD-2023-521818 | B131: 44948 | C131: 44956 | D131: Americas | E131: USA | F131: San Francisco | G131: Small Business | H131: Online | I131: A. Patel | J131: Networking | K131: NET-4155 | L131: 413.52 | M131: 1004.34 | N131: 0.111 | O131: 18
A132: ORD-2025-650719 | B132: 45700 | C132: 45716 | D132: Americas | E132: Brazil | F132: São Paulo | G132: Non-Profit | H132: Direct | I132: B. Chen | J132: Monitors | K132: MON-5179 | L132: 414.95 | M132: 1027.73 | N132: 0.063 | O132: 8
A133: ORD-2025-501927 | B133: 45719 | C133: 45740 | D133: Africa | E133: Nigeria | F133: Abuja | G133: Enterprise | H133: Direct | I133: H. Kim | J133: Accessories | K133: ACC-4056 | L133: 555.95 | M133: 468.09 | N133: 0.142 | O133: 11
A134: ORD-2023-430904 | B134: 44953 | C134: 44957 | D134: Europe | E134: United Kingdom | F134: Manchester | G134: Enterprise | H134: Online | I134: N. Brown | J134: Laptops | K134: LAP-9782 | L134: 941.2 | M134: 668.02 | N134: 0.22 | O134: 16
... A187: ORD-2023-399631 | B187: 45099 | C187: 45128 | D187: Europe | E187: France | F187: Lyon | G187: Corporate | H187: Retail | I187: J. Njeri | J187: Accessories | K187: ACC-3385 | L187: 734.34 | M187: 887.9 | N187: 0.025 | O187: 12
A188: ORD-2025-542939 | B188: 45670 | C188: 45696 | D188: Europe | E188: France | F188: Paris | G188: Non-Profit | I188: E. Garcia | J188: Monitors | K188: MON-1593 | L188: 594.74 | M188: 1020.69 | N188: 0.211 | O188: 6
A189: ORD-2023-521818 | B189: 44955 | C189: 44985 | D189: Asia | E189: India | F189: Bengaluru | G189: Non-Profit | H189: Retail | I189: B. Chen | J189: Accessories | K189: ACC-4631 | L189: 1262.1 | M189: 1395.53 | N189: 0.233 | O189: 25
A190: ORD-2023-825836 | B190: 45126 | C190: 45138 | D190: Americas | E190: Brazil | F190: Rio de Janeiro | G190: Corporate | H190: Retail | I190: C. Otieno | J190: Monitors | K190: MON-7869 | L190: 1334.64 | M190: 2273.42 | N190: 0.118 | O190: 14
A191: ORD-2024-503082 | B191: 45431 | C191: 45451 | D191: Americas | E191: Brazil | F191: Brasília | G191: Small Business | H191: Retail | I191: E. Garcia | J191: Monitors | K191: MON-4271 | L191: 1075.9 | M191: 1242.15 | N191: 0.012 | O191: 7
A192: ORD-2024-760799 | B192: 45325 | C192: 45341 | D192: Asia | E192: China | F192: Shenzhen | G192: Small Business | H192: Online | I192: H. Kim | J192: Laptops | K192: LAP-5531 | L192: 993.75 | M192: 1310.29 | N192: 0.215 | O192: 19
A193: ORD-2023-197661 | B193: 45146 | C193: 45160 | D193: Europe | E193: United Kingdom | F193: Birmingham | G193: Non-Profit | H193: Direct | I193: N. Brown | J193: Monitors | K193: MON-7511 | L193: 446.69 | M193: 967.25 | N193: 0.094 | O193: 10
A194: ORD-2024-212990 | B194: 45516 | C194: 45538 | D194: Americas | E194: USA | F194: Austin | G194: Consumer | H194: Distributor | I194: I. Johnson | J194: Laptops | K194: LAP-7979 | L194: 797.8 | M194: 886.22 | N194: 0.236 | O194: 36
A195: ORD-2023-925146 | B195: 45214 | C195: 45243 | D195: Asia | E195: China | F195: Shenzhen | G195: Non-Profit | H195: Distributor | I195: J. Njeri | J195: Printers | K195: PRN-4983 | L195: 986.44 | M195: 790.61 | N195: 0.072 | O195: 6
A196: ORD-2023-177794 | B196: 45050 | C196: 45072 | D196: Americas | E196: USA | F196: San Francisco | G196: Enterprise | H196: Online | I196: J. Njeri | J196: Networking | K196: NET-5941 | L196: 249.71 | M196: 361.33 | N196: 0.094 | O196: 12
A197: ORD-2024-444710 | B197: 45557 | C197: 45566 | D197: Americas | E197: Brazil | F197: São Paulo | G197: Non-Profit | H197: Online | I197: K. Singh | J197: Monitors | K197: MON-6341 | L197: 1378.8 | M197: 1952.04 | N197: 0.159 | O197: 19
A198: ORD-2024-668926 | B198: 45588 | C198: 45610 | D198: Asia | E198: Japan | F198: Osaka | G198: Non-Profit | H198: Direct | I198: B. Chen | J198: Phones | K198: PHN-9789 | L198: 1406.4 | M198: 1564.76 | N198: 0.185 | O198: 17
A199: ORD-2024-968374 | B199: 45333 | C199: 45354 | D199: Africa | E199: Kenya | F199: Kisumu | G199: Enterprise | H199: Online | I199: B. Chen | J199: Phones | K199: PHN-5082 | L199: 516.86 | M199: 852.54 | N199: 0.051 | O199: 14
A200: ORD-2023-575584 | B200: 44956 | C200: 44978 | D200: Europe | E200: Germany | F200: Munich | G200: Small Business | H200: Marketplace | I200: G. Dubois | J200: Networking | K200: NET-3460 | L200: 1142.88 | M200: 1465.29 | N200: 0.186 | O200: 7
... A236: ORD-2023-946143 | B236: 44999 | C236: 45015 | D236: Africa | E236: South Africa | F236: Cape Town | G236: Consumer | H236: Distributor | I236: K. Singh | J236: Components | K236: CMP-8230 | L236: 1309.77 | M236: 1589.07 | N236: 0.102 | O236: 10
A237: ORD-2024-281211 | B237: 45302 | C237: 45324 | D237: Asia | E237: Japan | F237: Nagoya | G237: Small Business | H237: Online | J237: Printers | K237: PRN-7816 | L237: 1237.68 | M237: 1432.8 | N237: 0.068 | O237: 13
A238: ORD-2024-805860 | B238: 45548 | C238: 45567 | D238: Africa | E238: Kenya | F238: Mombasa | G238: Small Business | H238: Retail | I238: M. Rossi | J238: Phones | K238: PHN-8804 | L238: 1338.99 | M238: 1765.76 | N238: 0.126 | O238: 24
A239: ORD-2025-132174 | B239: 45855 | C239: 45861 | D239: Americas | E239: Canada | F239: Vancouver | G239: Consumer | H239: Online | I239: H. Kim | J239: Components | K239: CMP-8851 | L239: 1364.89 | M239: 2757.54 | N239: 0.172 | O239: 61
A240: ORD-2023-964434 | B240: 45258 | C240: 45267 | D240: Asia | E240: India | F240: Delhi | G240: Enterprise | H240: Marketplace | I240: L. Okafor | J240: Phones | K240: PHN-2447 | L240: 699.33 | M240: 873.75 | N240: 0.235 | O240: 10
A241: ORD-2024-897622 | B241: 45381 | C241: 45406 | D241: Americas | E241: USA | F241: Austin | G241: Non-Profit | H241: Online | I241: G. Dubois | J241: Laptops | K241: LAP-2846 | L241: 160.82 | M241: 258.52 | N241: 0.13 | O241: 17
A242: ORD-2023-517216 | B242: 45188 | C242: 45207 | D242: Asia | E242: India | F242: Bengaluru | G242: Education | H242: Direct | I242: J. Njeri | J242: Printers | K242: PRN-5005 | L242: 385.32 | M242: 606.76 | N242: 0.086 | O242: 8
A243: ORD-2025-509940 | B243: 45793 | C243: 45804 | D243: Asia | E243: China | F243: Beijing | G243: Enterprise | H243: Online | I243: F. Müller | J243: Phones | K243: PHN-3800 | L243: 918.12 | M243: 1337.69 | N243: 0.095 | O243: 8
A244: ORD-2025-646342 | B244: 45871 | C244: 45877 | D244: Asia | E244: Japan | F244: Osaka | G244: Consumer | H244: Direct | I244: N. Brown | J244: Laptops | K244: LAP-4828 | L244: 1225.94 | M244: 1793.08 | N244: 0.136 | O244: 22
A245: ORD-2024-866535 | B245: 45630 | C245: 45638 | D245: Europe | E245: Germany | F245: Frankfurt | G245: Enterprise | H245: Marketplace | I245: B. Chen | J245: Printers | K245: PRN-5492 | L245: 72.06 | M245: 122.74 | N245: 0.238 | O245: 8
A246: ORD-2023-747341 | B246: 45035 | C246: 45044 | D246: Americas | E246: Brazil | F246: Rio de Janeiro | G246: Corporate | H246: Distributor | I246: M. Rossi | J246: Phones | K246: PHN-7132 | L246: 1013.54 | M246: 927.93 | N246: 0.175 | O246: 16
...

Sheet staging
A1: OrderID | B1: OrderDate | C1: Months | D1: FirstPurchase_Month | E1: CohortMonthIndex | F1: Quarter | G1: RequiredDate | H1: Corrected Required_Date | I1: LeadTime(Days) | J1: OnTime | K1: MeetsSLA | L1: Region | M1: Country | N1: City | O1: CustomerSegment | P1: Channel | Q1: Salesperson | R1: ProductCategory | S1: SKU | T1: UnitCost | U1: UnitPrice | V1: Discount | W1: DiscountPct | X1: High Discount Flag | Y1: Quantity | Z1: GrossRevenue | AA1: CostOfGoods | AB1: GrossProfit | AC1: MarginPct | AD1: Low_Medium_Cutoff | AE1: Medium_High_Cutoff | AF1: PriceBand
A2: ORD-2024-275203 | B2: 45362 | C2: =EOMONTH(Table2[[#This Row],[OrderDate]],-1)+1 -> 45352 | D2: =EOMONTH(_xlfn.MINIFS(B2:B632,M2:M632,Table2[[#This Row],[Country]]), -1) + 1 -> 44927 | F2: ="Q"&ROUNDUP(MONTH(B2)/3,0)&"-"&YEAR(B2) -> Q1-2024 | G2: 45388 | H2: =IF(G2<B2, B2+3, G2) -> 45388 | I2: =H2-B2 -> 26 | J2: =IF(I2 <= 7, 1, 0) -> 0 | K2: =IF(I2<=7,1,0) -> 0 | L2: Africa | M2: Kenya | N2: Kisumu | O2: Corporate | P2: Retail | Q2: C. Otieno | R2: Components | S2: CMP-8270 | T2: 279.24 | U2: 608.9 | V2: =IF(W2>0.3,0.3,W2) -> 0.112 | W2: 0.112 | X2: =IF(Table2[[#This Row],[DiscountPct]]>0.2,1,0) -> 0 | Y2: 9 | Z2: =Table2[[#This Row],[UnitPrice]]*Y2*(1-V2) -> 4866.3288 | AA2: =T2*Y2 -> 2513.16 | AB2: =Z2-AA2 -> 2353.1688 | AC2: =IF(Z2=0,0,AB2/Z2) -> 0.48356141 | AD2: =_xlfn.PERCENTILE.INC(S:S, 0.33) -> #NUM! | AE2: =_xlfn.PERCENTILE.INC(S:S, 0.66) -> #NUM! | AF2: =IF(Z2="","", IF(Z2<=AD2,"Low", IF(Z2<=AE2,"Medium","High") ) ) -> #NUM!
A3: ORD-2024-358795 | B3: 45588 | C3: =EOMONTH(Table2[[#This Row],[OrderDate]],-1)+1 -> 45566 | D3: =EOMONTH(_xlfn.MINIFS(B3:B633,M3:M633,Table2[[#This Row],[Country]]), -1) + 1 -> 44927 | F3: ="Q"&ROUNDUP(MONTH(B3)/3,0)&"-"&YEAR(B3) -> Q4-2024 | G3: 45587 | H3: =IF(G3<B3, B3+3, G3) -> 45591 | I3: =H3-B3 -> 3 | J3: =IF(I3 <= 7, 1, 0) -> 1 | K3: =IF(I3<=7,1,0) -> 1 | L3: Africa | M3: Nigeria | N3: Port Harcourt | O3: Education | P3: Online | Q3: J. Njeri | R3: Printers | S3: PRN-9322 | T3: 1084.39 | U3: 759.33 | V3: =IF(W3>0.3,0.3,W3) -> 0.237 | W3: 0.237 | X3: =IF(Table2[[#This Row],[DiscountPct]]>0.2,1,0) -> 1 | Y3: 31 | Z3: =Table2[[#This Row],[UnitPrice]]*Y3*(1-V3) -> 17960.432 | AA3: =T3*Y3 -> 33616.09 | AB3: =Z3-AA3 -> -15655.658 | AC3: =IF(Z3=0,0,AB3/Z3) -> -0.87167486 | AD3: =_xlfn.PERCENTILE.INC(S:S, 0.33) -> #NUM! | AE3: =_xlfn.PERCENTILE.INC(S:S, 0.66) -> #NUM! | AF3: =IF(Z3="","", IF(Z3<=AD3,"Low", IF(Z3<=AE3,"Medium","High") ) ) -> #NUM!
A4: ORD-2023-373538 | B4: 44985 | C4: =EOMONTH(Table2[[#This Row],[OrderDate]],-1)+1 -> 44958 | D4: =EOMONTH(_xlfn.MINIFS(B4:B634,M4:M634,Table2[[#This Row],[Country]]), -1) + 1 -> 44927 | F4: ="Q"&ROUNDUP(MONTH(B4)/3,0)&"-"&YEAR(B4) -> Q1-2023 | G4: 45010 | H4: =IF(G4<B4, B4+3, G4) -> 45010 | I4: =H4-B4 -> 25 | J4: =IF(I4 <= 7, 1, 0) -> 0 | K4: =IF(I4<=7,1,0) -> 0 | L4: Africa | M4: Kenya | N4: Nairobi | O4: Corporate | P4: Retail | Q4: I. Johnson | R4: Networking | S4: NET-9666 | T4: 1460.76 | U4: 30.66 | V4: =IF(W4>0.3,0.3,W4) -> 0.131 | W4: 0.131 | X4: =IF(Table2[[#This Row],[DiscountPct]]>0.2,1,0) -> 0 | Y4: 12 | Z4: =Table2[[#This Row],[UnitPrice]]*Y4*(1-V4) -> 319.72248 | AA4: =T4*Y4 -> 17529.12 | AB4: =Z4-AA4 -> -17209.398 | AC4: =IF(Z4=0,0,AB4/Z4) -> -53.826048 | AD4: =_xlfn.PERCENTILE.INC(S:S, 0.33) -> #NUM! | AE4: =_xlfn.PERCENTILE.INC(S:S, 0.66) -> #NUM! | AF4: =IF(Z4="","", IF(Z4<=AD4,"Low", IF(Z4<=AE4,"Medium","High") ) ) -> #NUM!
A5: ORD-2025-168148 | B5: 45745 | C5: =EOMONTH(Table2[[#This Row],[OrderDate]],-1)+1 -> 45717 | D5: =EOMONTH(_xlfn.MINIFS(B5:B635,M5:M635,Table2[[#This Row],[Country]]), -1) + 1 -> 44927 | F5: ="Q"&ROUNDUP(MONTH(B5)/3,0)&"-"&YEAR(B5) -> Q1-2025 | G5: 45749 | H5: =IF(G5<B5, B5+3, G5) -> 45749 | I5: =H5-B5 -> 4 | J5: =IF(I5 <= 7, 1, 0) -> 1 | K5: =IF(I5<=7,1,0) -> 1 | L5: Africa | M5: Nigeria | N5: Lagos | O5: Non-Profit | P5: Marketplace | Q5: G. Dubois | R5: Phones | S5: PHN-4556 | T5: 259.93 | U5: 255.94 | V5: =IF(W5>0.3,0.3,W5) -> 0.072 | W5: 0.072 | X5: =IF(Table2[[#This Row],[DiscountPct]]>0.2,1,0) -> 0 | Y5: 22 | Z5: =Table2[[#This Row],[UnitPrice]]*Y5*(1-V5) -> 5225.271 | AA5: =T5*Y5 -> 5718.46 | AB5: =Z5-AA5 -> -493.18896 | AC5: =IF(Z5=0,0,AB5/Z5) -> -0.094385335 | AD5: =_xlfn.PERCENTILE.INC(S:S, 0.33) -> #NUM! | AE5: =_xlfn.PERCENTILE.INC(S:S, 0.66) -> #NUM! | AF5: =IF(Z5="","", IF(Z5<=AD5,"Low", IF(Z5<=AE5,"Medium","High") ) ) -> #NUM!
A6: ORD-2023-824839 | B6: 45266 | C6: =EOMONTH(Table2[[#This Row],[OrderDate]],-1)+1 -> 45261 | D6: =EOMONTH(_xlfn.MINIFS(B6:B636,M6:M636,Table2[[#This Row],[Country]]), -1) + 1 -> 44986 | F6: ="Q"&ROUNDUP(MONTH(B6)/3,0)&"-"&YEAR(B6) -> Q4-2023 | G6: 45291 | H6: =IF(G6<B6, B6+3, G6) -> 45291 | I6: =H6-B6 -> 25 | J6: =IF(I6 <= 7, 1, 0) -> 0 | K6: =IF(I6<=7,1,0) -> 0 | L6: Asia | M6: Japan | N6: Osaka | O6: Consumer | P6: Retail | Q6: L. Okafor | R6: Printers | S6: PRN-8041 | T6: 663.03 | U6: 813.51 | V6: =IF(W6>0.3,0.3,W6) -> 0.102 | W6: 0.102 | X6: =IF(Table2[[#This Row],[DiscountPct]]>0.2,1,0) -> 0 | Y6: 15 | Z6: =Table2[[#This Row],[UnitPrice]]*Y6*(1-V6) -> 10957.98 | AA6: =T6*Y6 -> 9945.45 | AB6: =Z6-AA6 -> 1012.5297 | AC6: =IF(Z6=0,0,AB6/Z6) -> 0.092401129 | AD6: =_xlfn.PERCENTILE.INC(S:S, 0.33) -> #NUM! | AE6: =_xlfn.PERCENTILE.INC(S:S, 0.66) -> #NUM! | AF6: =IF(Z6="","", IF(Z6<=AD6,"Low", IF(Z6<=AE6,"Medium","High") ) ) -> #NUM!
A7: ORD-2023-723587 | B7: 44928 | C7: =EOMONTH(Table2[[#This Row],[OrderDate]],-1)+1 -> 44927 | D7: =EOMONTH(_xlfn.MINIFS(B7:B637,M7:M637,Table2[[#This Row],[Country]]), -1) + 1 -> 44927 | F7: ="Q"&ROUNDUP(MONTH(B7)/3,0)&"-"&YEAR(B7) -> Q1-2023 | G7: 44931 | H7: =IF(G7<B7, B7+3, G7) -> 44931 | I7: =H7-B7 -> 3 | J7: =IF(I7 <= 7, 1, 0) -> 1 | K7: =IF(I7<=7,1,0) -> 1 | L7: Americas | M7: Canada | N7: Toronto | O7: Corporate | P7: Distributor | Q7: B. Chen | R7: Laptops | S7: LAP-8555 | T7: 315.87 | U7: 591.68 | V7: =IF(W7>0.3,0.3,W7) -> 0 | W7: 0 | X7: =IF(Table2[[#This Row],[DiscountPct]]>0.2,1,0) -> 0 | Y7: 7 | Z7: =Table2[[#This Row],[UnitPrice]]*Y7*(1-V7) -> 4141.76 | AA7: =T7*Y7 -> 2211.09 | AB7: =Z7-AA7 -> 1930.67 | AC7: =IF(Z7=0,0,AB7/Z7) -> 0.46614724 | AD7: =_xlfn.PERCENTILE.INC(S:S, 0.33) -> #NUM! | AE7: =_xlfn.PERCENTILE.INC(S:S, 0.66) -> #NUM! | AF7: =IF(Z7="","", IF(Z7<=AD7,"Low", IF(Z7<=AE7,"Medium","High") ) ) -> #NUM!
A8: ORD-2024-336584 | B8: 45653 | C8: =EOMONTH(Table2[[#This Row],[OrderDate]],-1)+1 -> 45627 | D8: =EOMONTH(_xlfn.MINIFS(B8:B638,M8:M638,Table2[[#This Row],[Country]]), -1) + 1 -> 44958 | F8: ="Q"&ROUNDUP(MONTH(B8)/3,0)&"-"&YEAR(B8) -> Q4-2024 | G8: 45671 | H8: =IF(G8<B8, B8+3, G8) -> 45671 | I8: =H8-B8 -> 18 | J8: =IF(I8 <= 7, 1, 0) -> 0 | K8: =IF(I8<=7,1,0) -> 0 | L8: Asia | M8: India | N8: Bengaluru | O8: Small Business | P8: Marketplace | Q8: E. Garcia | R8: Monitors | S8: MON-8629 | T8: 586.07 | U8: 845.97 | V8: =IF(W8>0.3,0.3,W8) -> 0.147 | W8: 0.147 | X8: =IF(Table2[[#This Row],[DiscountPct]]>0.2,1,0) -> 0 | Y8: 4 | Z8: =Table2[[#This Row],[UnitPrice]]*Y8*(1-V8) -> 2886.4496 | AA8: =T8*Y8 -> 2344.28 | AB8: =Z8-AA8 -> 542.16964 | AC8: =IF(Z8=0,0,AB8/Z8) -> 0.1878327 | AD8: =_xlfn.PERCENTILE.INC(S:S, 0.33) -> #NUM! | AE8: =_xlfn.PERCENTILE.INC(S:S, 0.66) -> #NUM! | AF8: =IF(Z8="","", IF(Z8<=AD8,"Low", IF(Z8<=AE8,"Medium","High") ) ) -> #NUM!
A9: ORD-2023-112666 | B9: 44941 | C9: =EOMONTH(Table2[[#This Row],[OrderDate]],-1)+1 -> 44927 | D9: =EOMONTH(_xlfn.MINIFS(B9:B639,M9:M639,Table2[[#This Row],[Country]]), -1) + 1 -> 44927 | F9: ="Q"&ROUNDUP(MONTH(B9)/3,0)&"-"&YEAR(B9) -> Q1-2023 | G9: 44939 | H9: =IF(G9<B9, B9+3, G9) -> 44944 | I9: =H9-B9 -> 3 | J9: =IF(I9 <= 7, 1, 0) -> 1 | K9: =IF(I9<=7,1,0) -> 1 | L9: Africa | M9: Nigeria | N9: Abuja | O9: Education | P9: Online | Q9: O. Wang | R9: Printers | S9: PRN-6276 | T9: 28.38 | U9: 47.22 | V9: =IF(W9>0.3,0.3,W9) -> 0.194 | W9: 0.194 | X9: =IF(Table2[[#This Row],[DiscountPct]]>0.2,1,0) -> 0 | Y9: 18 | Z9: =Table2[[#This Row],[UnitPrice]]*Y9*(1-V9) -> 685.06776 | AA9: =T9*Y9 -> 510.84 | AB9: =Z9-AA9 -> 174.22776 | AC9: =IF(Z9=0,0,AB9/Z9) -> 0.25432194 | AD9: =_xlfn.PERCENTILE.INC(S:S, 0.33) -> #NUM! | AE9: =_xlfn.PERCENTILE.INC(S:S, 0.66) -> #NUM! | AF9: =IF(Z9="","", IF(Z9<=AD9,"Low", IF(Z9<=AE9,"Medium","High") ) ) -> #NUM!
A10: ORD-2024-589570 | B10: 45416 | C10: =EOMONTH(Table2[[#This Row],[OrderDate]],-1)+1 -> 45413 | D10: =EOMONTH(_xlfn.MINIFS(B10:B640,M10:M640,Table2[[#This Row],[Country]]), -1) + 1 -> 44958 | F10: ="Q"&ROUNDUP(MONTH(B10)/3,0)&"-"&YEAR(B10) -> Q2-2024 | G10: 45441 | H10: =IF(G10<B10, B10+3, G10) -> 45441 | I10: =H10-B10 -> 25 | J10: =IF(I10 <= 7, 1, 0) -> 0 | K10: =IF(I10<=7,1,0) -> 0 | L10: Africa | M10: Nigeria | N10: Abuja | O10: Non-Profit | P10: Marketplace | Q10: O. Wang | R10: Monitors | S10: MON-6892 | T10: 1295.34 | U10: 2530.81 | V10: =IF(W10>0.3,0.3,W10) -> 0.031 | W10: 0.031 | X10: =IF(Table2[[#This Row],[DiscountPct]]>0.2,1,0) -> 0 | Y10: 6 | Z10: =Table2[[#This Row],[UnitPrice]]*Y10*(1-V10) -> 14714.129 | AA10: =T10*Y10 -> 7772.04 | AB10: =Z10-AA10 -> 6942.0893 | AC10: =IF(Z10=0,0,AB10/Z10) -> 0.47179749 | AD10: =_xlfn.PERCENTILE.INC(S:S, 0.33) -> #NUM! | AE10: =_xlfn.PERCENTILE.INC(S:S, 0.66) -> #NUM! | AF10: =IF(Z10="","", IF(Z10<=AD10,"Low", IF(Z10<=AE10,"Medium","High") ) ) -> #NUM!
A11: ORD-2025-997421 | B11: 45798 | C11: =EOMONTH(Table2[[#This Row],[OrderDate]],-1)+1 -> 45778 | D11: =EOMONTH(_xlfn.MINIFS(B11:B641,M11:M641,Table2[[#This Row],[Country]]), -1) + 1 -> 44927 | F11: ="Q"&ROUNDUP(MONTH(B11)/3,0)&"-"&YEAR(B11) -> Q2-2025 | G11: 45817 | H11: =IF(G11<B11, B11+3, G11) -> 45817 | I11: =H11-B11 -> 19 | J11: =IF(I11 <= 7, 1, 0) -> 0 | K11: =IF(I11<=7,1,0) -> 0 | L11: Americas | M11: Brazil | N11: São Paulo | O11: Non-Profit | P11: Online | Q11: A. Patel | R11: Components | S11: CMP-3731 | T11: 1331.38 | U11: 2309.56 | V11: =IF(W11>0.3,0.3,W11) -> 0.149 | W11: 0.149 | X11: =IF(Table2[[#This Row],[DiscountPct]]>0.2,1,0) -> 0 | Y11: 31 | Z11: =Table2[[#This Row],[UnitPrice]]*Y11*(1-V11) -> 60928.502 | AA11: =T11*Y11 -> 41272.78 | AB11: =Z11-AA11 -> 19655.722 | AC11: =IF(Z11=0,0,AB11/Z11) -> 0.32260308 | AD11: =_xlfn.PERCENTILE.INC(S:S, 0.33) -> #NUM! | AE11: =_xlfn.PERCENTILE.INC(S:S, 0.66) -> #NUM! | AF11: =IF(Z11="","", IF(Z11<=AD11,"Low", IF(Z11<=AE11,"Medium","High") ) ) -> #NUM!
A12: ORD-2024-210687 | B12: 45319 | C12: =EOMONTH(Table2[[#This Row],[OrderDate]],-1)+1 -> 45292 | D12: =EOMONTH(_xlfn.MINIFS(B12:B642,M12:M642,Table2[[#This Row],[Country]]), -1) + 1 -> 44927 | F12: ="Q"&ROUNDUP(MONTH(B12)/3,0)&"-"&YEAR(B12) -> Q1-2024 | G12: 45331 | H12: =IF(G12<B12, B12+3, G12) -> 45331 | I12: =H12-B12 -> 12 | J12: =IF(I12 <= 7, 1, 0) -> 0 | K12: =IF(I12<=7,1,0) -> 0 | L12: Europe | M12: Germany | N12: Berlin | O12: Corporate | P12: Online | Q12: G. Dubois | R12: Accessories | S12: ACC-7938 | T12: 644.17 | U12: 700.12 | V12: =IF(W12>0.3,0.3,W12) -> 0.006 | W12: 0.006 | X12: =IF(Table2[[#This Row],[DiscountPct]]>0.2,1,0) -> 0 | Y12: 23 | Z12: =Table2[[#This Row],[UnitPrice]]*Y12*(1-V12) -> 16006.143 | AA12: =T12*Y12 -> 14815.91 | AB12: =Z12-AA12 -> 1190.2334 | AC12: =IF(Z12=0,0,AB12/Z12) -> 0.074361038 | AD12: =_xlfn.PERCENTILE.INC(S:S, 0.33) -> #NUM! | AE12: =_xlfn.PERCENTILE.INC(S:S, 0.66) -> #NUM! | AF12: =IF(Z12="","", IF(Z12<=AD12,"Low", IF(Z12<=AE12,"Medium","High") ) ) -> #NUM!
A13: ORD-2025-515515 | B13: 45660 | C13: =EOMONTH(Table2[[#This Row],[OrderDate]],-1)+1 -> 45658 | D13: =EOMONTH(_xlfn.MINIFS(B13:B643,M13:M643,Table2[[#This Row],[Country]]), -1) + 1 -> 44986 | F13: ="Q"&ROUNDUP(MONTH(B13)/3,0)&"-"&YEAR(B13) -> Q1-2025 | G13: 45680 | H13: =IF(G13<B13, B13+3, G13) -> 45680 | I13: =H13-B13 -> 20 | J13: =IF(I13 <= 7, 1, 0) -> 0 | K13: =IF(I13<=7,1,0) -> 0 | L13: Asia | M13: Japan | N13: Osaka | O13: Corporate | P13: Distributor | Q13: F. Müller | R13: Phones | S13: PHN-7019 | T13: 908.6 | U13: 691.37 | V13: =IF(W13>0.3,0.3,W13) -> 0.25 | W13: 0.25 | X13: =IF(Table2[[#This Row],[DiscountPct]]>0.2,1,0) -> 1 | Y13: 20 | Z13: =Table2[[#This Row],[UnitPrice]]*Y13*(1-V13) -> 10370.55 | AA13: =T13*Y13 -> 18172 | AB13: =Z13-AA13 -> -7801.45 | AC13: =IF(Z13=0,0,AB13/Z13) -> -0.75226965 | AD13: =_xlfn.PERCENTILE.INC(S:S, 0.33) -> #NUM! | AE13: =_xlfn.PERCENTILE.INC(S:S, 0.66) -> #NUM! | AF13: =IF(Z13="","", IF(Z13<=AD13,"Low", IF(Z13<=AE13,"Medium","High") ) ) -> #NUM!
... A121: ORD-2025-956101 | B121: 45847 | C121: =EOMONTH(Table2[[#This Row],[OrderDate]],-1)+1 -> 45839 | D121: =EOMONTH(_xlfn.MINIFS(B121:B751,M121:M751,Table2[[#This Row],[Country]]), -1) + 1 -> 44986 | F121: ="Q"&ROUNDUP(MONTH(B121)/3,0)&"-"&YEAR(B121) -> Q3-2025 | G121: 45856 | H121: =IF(G121<B121, B121+3, G121) -> 45856 | I121: =H121-B121 -> 9 | J121: =IF(I121 <= 7, 1, 0) -> 0 | K121: =IF(I121<=7,1,0) -> 0 | L121: Americas | M121: Canada | N121: Vancouver | O121: Education | P121: Distributor | Q121: I. Johnson | R121: Laptops | S121: LAP-2218 | T121: 57.96 | U121: 88.51 | V121: =IF(W121>0.3,0.3,W121) -> 0.043 | W121: 0.043 | X121: =IF(Table2[[#This Row],[DiscountPct]]>0.2,1,0) -> 0 | Y121: 7 | Z121: =Table2[[#This Row],[UnitPrice]]*Y121*(1-V121) -> 592.92849 | AA121: =T121*Y121 -> 405.72 | AB121: =Z121-AA121 -> 187.20849 | AC121: =IF(Z121=0,0,AB121/Z121) -> 0.31573536 | AD121: =_xlfn.PERCENTILE.INC(S:S, 0.33) -> #NUM! | AE121: =_xlfn.PERCENTILE.INC(S:S, 0.66) -> #NUM! | AF121: =IF(Z121="","", IF(Z121<=AD121,"Low", IF(Z121<=AE121,"Medium","High") ) ) -> #NUM!
A122: ORD-2025-184082 | B122: 45827 | C122: =EOMONTH(Table2[[#This Row],[OrderDate]],-1)+1 -> 45809 | D122: =EOMONTH(_xlfn.MINIFS(B122:B752,M122:M752,Table2[[#This Row],[Country]]), -1) + 1 -> 44927 | F122: ="Q"&ROUNDUP(MONTH(B122)/3,0)&"-"&YEAR(B122) -> Q2-2025 | G122: 45850 | H122: =IF(G122<B122, B122+3, G122) -> 45850 | I122: =H122-B122 -> 23 | J122: =IF(I122 <= 7, 1, 0) -> 0 | K122: =IF(I122<=7,1,0) -> 0 | L122: Europe | M122: United Kingdom | O122: Non-Profit | P122: Direct | Q122: Unassigned | R122: Networking | S122: NET-6370 | T122: 801.24 | U122: 1959.09 | V122: =IF(W122>0.3,0.3,W122) -> 0.123 | W122: 0.123 | X122: =IF(Table2[[#This Row],[DiscountPct]]>0.2,1,0) -> 0 | Y122: 23 | Z122: =Table2[[#This Row],[UnitPrice]]*Y122*(1-V122) -> 39516.804 | AA122: =T122*Y122 -> 18428.52 | AB122: =Z122-AA122 -> 21088.284 | AC122: =IF(Z122=0,0,AB122/Z122) -> 0.53365359 | AD122: =_xlfn.PERCENTILE.INC(S:S, 0.33) -> #NUM! | AE122: =_xlfn.PERCENTILE.INC(S:S, 0.66) -> #NUM! | AF122: =IF(Z122="","", IF(Z122<=AD122,"Low", IF(Z122<=AE122,"Medium","High") ) ) -> #NUM!
A123: ORD-2023-576840 | B123: 45249 | C123: =EOMONTH(Table2[[#This Row],[OrderDate]],-1)+1 -> 45231 | D123: =EOMONTH(_xlfn.MINIFS(B123:B753,M123:M753,Table2[[#This Row],[Country]]), -1) + 1 -> 44927 | F123: ="Q"&ROUNDUP(MONTH(B123)/3,0)&"-"&YEAR(B123) -> Q4-2023 | G123: 45273 | H123: =IF(G123<B123, B123+3, G123) -> 45273 | I123: =H123-B123 -> 24 | J123: =IF(I123 <= 7, 1, 0) -> 0 | K123: =IF(I123<=7,1,0) -> 0 | L123: Europe | M123: France | N123: Lyon | O123: Non-Profit | P123: Direct | Q123: H. Kim | R123: Monitors | S123: MON-3745 | T123: 1297.42 | U123: 2742.97 | V123: =IF(W123>0.3,0.3,W123) -> 0.069 | W123: 0.069 | X123: =IF(Table2[[#This Row],[DiscountPct]]>0.2,1,0) -> 0 | Y123: 9 | Z123: =Table2[[#This Row],[UnitPrice]]*Y123*(1-V123) -> 22983.346 | AA123: =T123*Y123 -> 11676.78 | AB123: =Z123-AA123 -> 11306.566 | AC123: =IF(Z123=0,0,AB123/Z123) -> 0.49194603 | AD123: =_xlfn.PERCENTILE.INC(S:S, 0.33) -> #NUM! | AE123: =_xlfn.PERCENTILE.INC(S:S, 0.66) -> #NUM! | AF123: =IF(Z123="","", IF(Z123<=AD123,"Low", IF(Z123<=AE123,"Medium","High") ) ) -> #NUM!
A124: ORD-2023-178249 | B124: 45289 | C124: =EOMONTH(Table2[[#This Row],[OrderDate]],-1)+1 -> 45261 | D124: =EOMONTH(_xlfn.MINIFS(B124:B754,M124:M754,Table2[[#This Row],[Country]]), -1) + 1 -> 44927 | F124: ="Q"&ROUNDUP(MONTH(B124)/3,0)&"-"&YEAR(B124) -> Q4-2023 | G124: 45311 | H124: =IF(G124<B124, B124+3, G124) -> 45311 | I124: =H124-B124 -> 22 | J124: =IF(I124 <= 7, 1, 0) -> 0 | K124: =IF(I124<=7,1,0) -> 0 | L124: Africa | M124: Kenya | N124: Kisumu | O124: Corporate | P124: Direct | Q124: L. Okafor | R124: Phones | S124: PHN-7924 | T124: 1395.49 | U124: 1679.42 | V124: =IF(W124>0.3,0.3,W124) -> 0.203 | W124: 0.203 | X124: =IF(Table2[[#This Row],[DiscountPct]]>0.2,1,0) -> 1 | Y124: 12 | Z124: =Table2[[#This Row],[UnitPrice]]*Y124*(1-V124) -> 16061.973 | AA124: =T124*Y124 -> 16745.88 | AB124: =Z124-AA124 -> -683.90712 | AC124: =IF(Z124=0,0,AB124/Z124) -> -0.042579272 | AD124: =_xlfn.PERCENTILE.INC(S:S, 0.33) -> #NUM! | AE124: =_xlfn.PERCENTILE.INC(S:S, 0.66) -> #NUM! | AF124: =IF(Z124="","", IF(Z124<=AD124,"Low", IF(Z124<=AE124,"Medium","High") ) ) -> #NUM!
A125: ORD-2024-588972 | B125: 45598 | C125: =EOMONTH(Table2[[#This Row],[OrderDate]],-1)+1 -> 45597 | D125: =EOMONTH(_xlfn.MINIFS(B125:B755,M125:M755,Table2[[#This Row],[Country]]), -1) + 1 -> 44927 | F125: ="Q"&ROUNDUP(MONTH(B125)/3,0)&"-"&YEAR(B125) -> Q4-2024 | G125: 45625 | H125: =IF(G125<B125, B125+3, G125) -> 45625 | I125: =H125-B125 -> 27 | J125: =IF(I125 <= 7, 1, 0) -> 0 | K125: =IF(I125<=7,1,0) -> 0 | L125: Americas | M125: Brazil | N125: Brasília | O125: Small Business | P125: Direct | Q125: I. Johnson | R125: Networking | S125: NET-8561 | T125: 1363.51 | U125: 1433.9 | V125: =IF(W125>0.3,0.3,W125) -> 0.057 | W125: 0.057 | X125: =IF(Table2[[#This Row],[DiscountPct]]>0.2,1,0) -> 0 | Y125: 8 | Z125: =Table2[[#This Row],[UnitPrice]]*Y125*(1-V125) -> 10817.342 | AA125: =T125*Y125 -> 10908.08 | AB125: =Z125-AA125 -> -90.7384 | AC125: =IF(Z125=0,0,AB125/Z125) -> -0.0083882347 | AD125: =_xlfn.PERCENTILE.INC(S:S, 0.33) -> #NUM! | AE125: =_xlfn.PERCENTILE.INC(S:S, 0.66) -> #NUM! | AF125: =IF(Z125="","", IF(Z125<=AD125,"Low", IF(Z125<=AE125,"Medium","High") ) ) -> #NUM!
A126: ORD-2023-603238 | B126: 45159 | C126: =EOMONTH(Table2[[#This Row],[OrderDate]],-1)+1 -> 45139 | D126: =EOMONTH(_xlfn.MINIFS(B126:B756,M126:M756,Table2[[#This Row],[Country]]), -1) + 1 -> 44986 | F126: ="Q"&ROUNDUP(MONTH(B126)/3,0)&"-"&YEAR(B126) -> Q3-2023 | G126: 45173 | H126: =IF(G126<B126, B126+3, G126) -> 45173 | I126: =H126-B126 -> 14 | J126: =IF(I126 <= 7, 1, 0) -> 0 | K126: =IF(I126<=7,1,0) -> 0 | L126: Americas | M126: Canada | N126: Montreal | O126: Education | P126: Distributor | Q126: F. Müller | R126: Components | S126: CMP-2136 | T126: 178.19 | U126: 284.43 | V126: =IF(W126>0.3,0.3,W126) -> 0.089 | W126: 0.089 | X126: =IF(Table2[[#This Row],[DiscountPct]]>0.2,1,0) -> 0 | Y126: 8 | Z126: =Table2[[#This Row],[UnitPrice]]*Y126*(1-V126) -> 2072.9258 | AA126: =T126*Y126 -> 1425.52 | AB126: =Z126-AA126 -> 647.40584 | AC126: =IF(Z126=0,0,AB126/Z126) -> 0.312315 | AD126: =_xlfn.PERCENTILE.INC(S:S, 0.33) -> #NUM! | AE126: =_xlfn.PERCENTILE.INC(S:S, 0.66) -> #NUM! | AF126: =IF(Z126="","", IF(Z126<=AD126,"Low", IF(Z126<=AE126,"Medium","High") ) ) -> #NUM!
A127: ORD-2023-883066 | B127: 45150 | C127: =EOMONTH(Table2[[#This Row],[OrderDate]],-1)+1 -> 45139 | D127: =EOMONTH(_xlfn.MINIFS(B127:B757,M127:M757,Table2[[#This Row],[Country]]), -1) + 1 -> 44927 | F127: ="Q"&ROUNDUP(MONTH(B127)/3,0)&"-"&YEAR(B127) -> Q3-2023 | G127: 45175 | H127: =IF(G127<B127, B127+3, G127) -> 45175 | I127: =H127-B127 -> 25 | J127: =IF(I127 <= 7, 1, 0) -> 0 | K127: =IF(I127<=7,1,0) -> 0 | L127: Asia | M127: China | N127: Shanghai | O127: Small Business | P127: Retail | Q127: B. Chen | R127: Components | S127: CMP-6352 | T127: 950.77 | U127: 694.78 | V127: =IF(W127>0.3,0.3,W127) -> 0.084 | W127: 0.084 | X127: =IF(Table2[[#This Row],[DiscountPct]]>0.2,1,0) -> 0 | Y127: 14 | Z127: =Table2[[#This Row],[UnitPrice]]*Y127*(1-V127) -> 8909.8587 | AA127: =T127*Y127 -> 13310.78 | AB127: =Z127-AA127 -> -4400.9213 | AC127: =IF(Z127=0,0,AB127/Z127) -> -0.49393839 | AD127: =_xlfn.PERCENTILE.INC(S:S, 0.33) -> #NUM! | AE127: =_xlfn.PERCENTILE.INC(S:S, 0.66) -> #NUM! | AF127: =IF(Z127="","", IF(Z127<=AD127,"Low", IF(Z127<=AE127,"Medium","High") ) ) -> #NUM!
A128: ORD-2024-584090 | B128: 45450 | C128: =EOMONTH(Table2[[#This Row],[OrderDate]],-1)+1 -> 45444 | D128: =EOMONTH(_xlfn.MINIFS(B128:B758,M128:M758,Table2[[#This Row],[Country]]), -1) + 1 -> 44927 | F128: ="Q"&ROUNDUP(MONTH(B128)/3,0)&"-"&YEAR(B128) -> Q2-2024 | G128: 45469 | H128: =IF(G128<B128, B128+3, G128) -> 45469 | I128: =H128-B128 -> 19 | J128: =IF(I128 <= 7, 1, 0) -> 0 | K128: =IF(I128<=7,1,0) -> 0 | L128: Europe | M128: Germany | N128: Berlin | O128: Non-Profit | P128: Marketplace | Q128: M. Rossi | R128: Components | S128: CMP-2040 | T128: 1064.32 | U128: 1848.39 | V128: =IF(W128>0.3,0.3,W128) -> 0.073 | W128: 0.073 | X128: =IF(Table2[[#This Row],[DiscountPct]]>0.2,1,0) -> 0 | Y128: 38 | Z128: =Table2[[#This Row],[UnitPrice]]*Y128*(1-V128) -> 65111.386 | AA128: =T128*Y128 -> 40444.16 | AB128: =Z128-AA128 -> 24667.226 | AC128: =IF(Z128=0,0,AB128/Z128) -> 0.37884658 | AD128: =_xlfn.PERCENTILE.INC(S:S, 0.33) -> #NUM! | AE128: =_xlfn.PERCENTILE.INC(S:S, 0.66) -> #NUM! | AF128: =IF(Z128="","", IF(Z128<=AD128,"Low", IF(Z128<=AE128,"Medium","High") ) ) -> #NUM!
A129: ORD-2025-537785 | B129: 45874 | C129: =EOMONTH(Table2[[#This Row],[OrderDate]],-1)+1 -> 45870 | D129: =EOMONTH(_xlfn.MINIFS(B129:B759,M129:M759,Table2[[#This Row],[Country]]), -1) + 1 -> 44927 | F129: ="Q"&ROUNDUP(MONTH(B129)/3,0)&"-"&YEAR(B129) -> Q3-2025 | G129: 45883 | H129: =IF(G129<B129, B129+3, G129) -> 45883 | I129: =H129-B129 -> 9 | J129: =IF(I129 <= 7, 1, 0) -> 0 | K129: =IF(I129<=7,1,0) -> 0 | L129: Europe | M129: United Kingdom | N129: London | O129: Non-Profit | P129: Direct | Q129: E. Garcia | R129: Components | S129: CMP-6346 | T129: 41.76 | U129: 45.19 | V129: =IF(W129>0.3,0.3,W129) -> 0.179 | W129: 0.179 | X129: =IF(Table2[[#This Row],[DiscountPct]]>0.2,1,0) -> 0 | Y129: 23 | Z129: =Table2[[#This Row],[UnitPrice]]*Y129*(1-V129) -> 853.32277 | AA129: =T129*Y129 -> 960.48 | AB129: =Z129-AA129 -> -107.15723 | AC129: =IF(Z129=0,0,AB129/Z129) -> -0.12557643 | AD129: =_xlfn.PERCENTILE.INC(S:S, 0.33) -> #NUM! | AE129: =_xlfn.PERCENTILE.INC(S:S, 0.66) -> #NUM! | AF129: =IF(Z129="","", IF(Z129<=AD129,"Low", IF(Z129<=AE129,"Medium","High") ) ) -> #NUM!
A130: ORD-2024-605518 | B130: 45442 | C130: =EOMONTH(Table2[[#This Row],[OrderDate]],-1)+1 -> 45413 | D130: =EOMONTH(_xlfn.MINIFS(B130:B760,M130:M760,Table2[[#This Row],[Country]]), -1) + 1 -> 44927 | F130: ="Q"&ROUNDUP(MONTH(B130)/3,0)&"-"&YEAR(B130) -> Q2-2024 | G130: 45456 | H130: =IF(G130<B130, B130+3, G130) -> 45456 | I130: =H130-B130 -> 14 | J130: =IF(I130 <= 7, 1, 0) -> 0 | K130: =IF(I130<=7,1,0) -> 0 | L130: Americas | M130: USA | N130: San Francisco | O130: Small Business | P130: Retail | Q130: F. Müller | R130: Phones | S130: PHN-4356 | T130: 157.78 | U130: 361.1 | V130: =IF(W130>0.3,0.3,W130) -> 0.187 | W130: 0.187 | X130: =IF(Table2[[#This Row],[DiscountPct]]>0.2,1,0) -> 0 | Y130: 9 | Z130: =Table2[[#This Row],[UnitPrice]]*Y130*(1-V130) -> 2642.1687 | AA130: =T130*Y130 -> 1420.02 | AB130: =Z130-AA130 -> 1222.1487 | AC130: =IF(Z130=0,0,AB130/Z130) -> 0.46255514 | AD130: =_xlfn.PERCENTILE.INC(S:S, 0.33) -> #NUM! | AE130: =_xlfn.PERCENTILE.INC(S:S, 0.66) -> #NUM! | AF130: =IF(Z130="","", IF(Z130<=AD130,"Low", IF(Z130<=AE130,"Medium","High") ) ) -> #NUM!
A131: ORD-2023-521818 | B131: 44948 | C131: =EOMONTH(Table2[[#This Row],[OrderDate]],-1)+1 -> 44927 | D131: =EOMONTH(_xlfn.MINIFS(B131:B761,M131:M761,Table2[[#This Row],[Country]]), -1) + 1 -> 44927 | F131: ="Q"&ROUNDUP(MONTH(B131)/3,0)&"-"&YEAR(B131) -> Q1-2023 | G131: 44956 | H131: =IF(G131<B131, B131+3, G131) -> 44956 | I131: =H131-B131 -> 8 | J131: =IF(I131 <= 7, 1, 0) -> 0 | K131: =IF(I131<=7,1,0) -> 0 | L131: Americas | M131: USA | N131: San Francisco | O131: Small Business | P131: Online | Q131: A. Patel | R131: Networking | S131: NET-4155 | T131: 413.52 | U131: 1004.34 | V131: =IF(W131>0.3,0.3,W131) -> 0.111 | W131: 0.111 | X131: =IF(Table2[[#This Row],[DiscountPct]]>0.2,1,0) -> 0 | Y131: 18 | Z131: =Table2[[#This Row],[UnitPrice]]*Y131*(1-V131) -> 16071.449 | AA131: =T131*Y131 -> 7443.36 | AB131: =Z131-AA131 -> 8628.0887 | AC131: =IF(Z131=0,0,AB131/Z131) -> 0.53685818 | AD131: =_xlfn.PERCENTILE.INC(S:S, 0.33) -> #NUM! | AE131: =_xlfn.PERCENTILE.INC(S:S, 0.66) -> #NUM! | AF131: =IF(Z131="","", IF(Z131<=AD131,"Low", IF(Z131<=AE131,"Medium","High") ) ) -> #NUM!
A132: ORD-2025-650719 | B132: 45700 | C132: =EOMONTH(Table2[[#This Row],[OrderDate]],-1)+1 -> 45689 | D132: =EOMONTH(_xlfn.MINIFS(B132:B762,M132:M762,Table2[[#This Row],[Country]]), -1) + 1 -> 44927 | F132: ="Q"&ROUNDUP(MONTH(B132)/3,0)&"-"&YEAR(B132) -> Q1-2025 | G132: 45716 | H132: =IF(G132<B132, B132+3, G132) -> 45716 | I132: =H132-B132 -> 16 | J132: =IF(I132 <= 7, 1, 0) -> 0 | K132: =IF(I132<=7,1,0) -> 0 | L132: Americas | M132: Brazil | N132: São Paulo | O132: Non-Profit | P132: Direct | Q132: B. Chen | R132: Monitors | S132: MON-5179 | T132: 414.95 | U132: 1027.73 | V132: =IF(W132>0.3,0.3,W132) -> 0.063 | W132: 0.063 | X132: =IF(Table2[[#This Row],[DiscountPct]]>0.2,1,0) -> 0 | Y132: 8 | Z132: =Table2[[#This Row],[UnitPrice]]*Y132*(1-V132) -> 7703.8641 | AA132: =T132*Y132 -> 3319.6 | AB132: =Z132-AA132 -> 4384.2641 | AC132: =IF(Z132=0,0,AB132/Z132) -> 0.56909936 | AD132: =_xlfn.PERCENTILE.INC(S:S, 0.33) -> #NUM! | AE132: =_xlfn.PERCENTILE.INC(S:S, 0.66) -> #NUM! | AF132: =IF(Z132="","", IF(Z132<=AD132,"Low", IF(Z132<=AE132,"Medium","High") ) ) -> #NUM!
A133: ORD-2025-501927 | B133: 45719 | C133: =EOMONTH(Table2[[#This Row],[OrderDate]],-1)+1 -> 45717 | D133: =EOMONTH(_xlfn.MINIFS(B133:B763,M133:M763,Table2[[#This Row],[Country]]), -1) + 1 -> 44958 | F133: ="Q"&ROUNDUP(MONTH(B133)/3,0)&"-"&YEAR(B133) -> Q1-2025 | G133: 45740 | H133: =IF(G133<B133, B133+3, G133) -> 45740 | I133: =H133-B133 -> 21 | J133: =IF(I133 <= 7, 1, 0) -> 0 | K133: =IF(I133<=7,1,0) -> 0 | L133: Africa | M133: Nigeria | N133: Abuja | O133: Enterprise | P133: Direct | Q133: H. Kim | R133: Accessories | S133: ACC-4056 | T133: 555.95 | U133: 468.09 | V133: =IF(W133>0.3,0.3,W133) -> 0.142 | W133: 0.142 | X133: =IF(Table2[[#This Row],[DiscountPct]]>0.2,1,0) -> 0 | Y133: 11 | Z133: =Table2[[#This Row],[UnitPrice]]*Y133*(1-V133) -> 4417.8334 | AA133: =T133*Y133 -> 6115.45 | AB133: =Z133-AA133 -> -1697.6166 | AC133: =IF(Z133=0,0,AB133/Z133) -> -0.38426451 | AD133: =_xlfn.PERCENTILE.INC(S:S, 0.33) -> #NUM! | AE133: =_xlfn.PERCENTILE.INC(S:S, 0.66) -> #NUM! | AF133: =IF(Z133="","", IF(Z133<=AD133,"Low", IF(Z133<=AE133,"Medium","High") ) ) -> #NUM!
A134: ORD-2023-430904 | B134: 44953 | C134: =EOMONTH(Table2[[#This Row],[OrderDate]],-1)+1 -> 44927 | D134: =EOMONTH(_xlfn.MINIFS(B134:B764,M134:M764,Table2[[#This Row],[Country]]), -1) + 1 -> 44927 | F134: ="Q"&ROUNDUP(MONTH(B134)/3,0)&"-"&YEAR(B134) -> Q1-2023 | G134: 44957 | H134: =IF(G134<B134, B134+3, G134) -> 44957 | I134: =H134-B134 -> 4 | J134: =IF(I134 <= 7, 1, 0) -> 1 | K134: =IF(I134<=7,1,0) -> 1 | L134: Europe | M134: United Kingdom | N134: Manchester | O134: Enterprise | P134: Online | Q134: N. Brown | R134: Laptops | S134: LAP-9782 | T134: 941.2 | U134: 668.02 | V134: =IF(W134>0.3,0.3,W134) -> 0.22 | W134: 0.22 | X134: =IF(Table2[[#This Row],[DiscountPct]]>0.2,1,0) -> 1 | Y134: 16 | Z134: =Table2[[#This Row],[UnitPrice]]*Y134*(1-V134) -> 8336.8896 | AA134: =T134*Y134 -> 15059.2 | AB134: =Z134-AA134 -> -6722.3104 | AC134: =IF(Z134=0,0,AB134/Z134) -> -0.80633314 | AD134: =_xlfn.PERCENTILE.INC(S:S, 0.33) -> #NUM! | AE134: =_xlfn.PERCENTILE.INC(S:S, 0.66) -> #NUM! | AF134: =IF(Z134="","", IF(Z134<=AD134,"Low", IF(Z134<=AE134,"Medium","High") ) ) -> #NUM!
... A632: ORD-2025-728935 | B632: 45716 | C632: =EOMONTH(Table2[[#This Row],[OrderDate]],-1)+1 -> 45689 | D632: =EOMONTH(_xlfn.MINIFS(B632:B1262,M632:M1262,Table2[[#This Row],[Country]]), -1) + 1 -> 45689 | F632: ="Q"&ROUNDUP(MONTH(B632)/3,0)&"-"&YEAR(B632) -> Q1-2025 | G632: 45726 | H632: =IF(G632<B632, B632+3, G632) -> 45726 | I632: =H632-B632 -> 10 | J632: =IF(I632 <= 7, 1, 0) -> 0 | K632: =IF(I632<=7,1,0) -> 0 | L632: Asia | M632: Japan | N632: Osaka | O632: Education | P632: Distributor | Q632: N. Brown | R632: Laptops | S632: LAP-3017 | T632: 51.86 | U632: 45.98 | V632: =IF(W632>0.3,0.3,W632) -> 0.173 | W632: 0.173 | X632: =IF(Table2[[#This Row],[DiscountPct]]>0.2,1,0) -> 0 | Y632: 7 | Z632: =Table2[[#This Row],[UnitPrice]]*Y632*(1-V632) -> 266.17822 | AA632: =T632*Y632 -> 363.02 | AB632: =Z632-AA632 -> -96.84178 | AC632: =IF(Z632=0,0,AB632/Z632) -> -0.36382308 | AD632: =_xlfn.PERCENTILE.INC(S:S, 0.33) -> #NUM! | AE632: =_xlfn.PERCENTILE.INC(S:S, 0.66) -> #NUM! | AF632: =IF(Z632="","", IF(Z632<=AD632,"Low", IF(Z632<=AE632,"Medium","High") ) ) -> #NUM!

Sheet Pivot 1
A2: Row Labels | D2: Sum of GrossRevenue | E2: Column Labels
A3: Africa | D3: Row Labels | E3: Apr-2023 | F3: Apr-2024 | G3: Apr-2025 | H3: Aug-2023 | I3: Aug-2024 | J3: Aug-2025 | K3: Dec-2023 | L3: Dec-2024 | M3: Feb-2023 | N3: Feb-2024 | O3: Feb-2025 | P3: Jan-2023 | Q3: Jan-2024 | R3: Jan-2025 | S3: Jul-2023 | T3: Jul-2024 | U3: Jul-2025 | V3: Jun-2023 | W3: Jun-2024 | X3: Jun-2025 | Y3: Mar-2023 | Z3: Mar-2024 | AA3: Mar-2025 | AB3: May-2023 | AC3: May-2024 | AD3: May-2025 | AE3: Nov-2023 | AF3: Nov-2024 | AG3: Oct-2023 | AH3: Oct-2024 | AI3: Sep-2023 | AJ3: Sep-2024 | AK3: Sep-2025 | AL3: Grand Total
A4: Kenya | D4: Brazil | E4: 12248.676 | F4: 57491.063 | G4: 68920.107 | H4: 37330.003 | I4: 41358.42 | J4: 45754.744 | K4: 61471.697 | M4: 24894.431 | N4: 39239.198 | O4: 70563.592 | P4: 1801.4076 | Q4: 8567.3925 | R4: 22987.328 | S4: 93430.735 | T4: 10937.52 | U4: 38096.184 | V4: 46991.747 | W4: 41658.527 | Y4: 24523.007 | Z4: 110.1492 | AA4: 16257.34 | AB4: 27194.152 | AC4: 9469.7678 | AD4: 67596.422 | AE4: 24161.263 | AF4: 11939.431 | AG4: 16213.633 | AI4: 7071.6331 | AJ4: 85419.018 | AK4: 24172.045 | AL4: 1037870.6
A5: Kisumu | D5: Canada | E5: 15618.845 | G5: 7901.5042 | H5: 52625.804 | I5: 7466.3064 | J5: 24972.288 | K5: 14466.951 | L5: 20713.04 | M5: 26150.364 | N5: 9774.3888 | O5: 8128.5187 | P5: 4141.76 | Q5: 19139.594 | S5: 29536.716 | T5: 79082.507 | U5: 141645.57 | V5: 46226.12 | W5: 55516.604 | X5: 5335.5655 | Y5: 17453.344 | Z5: 21931.504 | AC5: 17930.495 | AD5: 76122.593 | AF5: 60697.471 | AG5: 27756.432 | AI5: 15530.93 | AJ5: 64160.245 | AK5: 12597.522 | AL5: 882622.98
A6: Mombasa | D6: China | E6: 23379.011 | F6: 14197.064 | H6: 64096.735 | J6: 33684.351 | K6: 23668.56 | L6: 77129.274 | M6: 10869.183 | N6: 79081.561 | P6: 11406.96 | R6: 56274.474 | T6: 50774.407 | U6: 20703.052 | V6: 5769.2758 | W6: 70180.56 | X6: 55548.647 | Y6: 13437.3 | Z6: 45749.976 | AA6: 9378.6258 | AB6: 49097.717 | AD6: 9684.8756 | AF6: 4071.8 | AG6: 66630.072 | AH6: 68861.98 | AI6: 14108.168 | AJ6: 21270.483 | AL6: 899054.11
A7: Nairobi | D7: France | E7: 40811.052 | F7: 16219.345 | G7: 33208.325 | H7: 36549.429 | I7: 9189.1635 | J7: 68199.913 | K7: 28412.1 | L7: 32011.667 | M7: 39546.775 | N7: 20654.545 | O7: 12040.644 | P7: 9847.2359 | Q7: 29263.361 | R7: 20050.102 | S7: 60768.603 | T7: 27907.425 | V7: 10388.43 | X7: 17419.587 | Z7: 45104.931 | AC7: 43635.435 | AD7: 5331.6696 | AE7: 22983.346 | AF7: 67281.057 | AG7: 5159.7894 | AH7: 41419.524 | AI7: 14877.464 | AL7: 758280.92
A8: Nakuru | D8: Germany | E8: 104633.05 | F8: 37482.346 | G8: 5810.4845 | H8: 215.1984 | I8: 47066.844 | J8: 56176.778 | K8: 56963.241 | L8: 78869.294 | M8: 142962.67 | N8: 321.93291 | O8: 30546.068 | P8: 13921.506 | Q8: 41020.91 | S8: 14114.069 | V8: 5189.8836 | W8: 65111.386 | X8: 56166.984 | Y8: 6271.3802 | Z8: 68292.728 | AA8: 16870.42 | AB8: 17964.404 | AC8: 32187.988 | AD8: 10666.229 | AE8: 7643.265 | AF8: 12955.825 | AL8: 929424.89
A9: Nigeria | D9: India | E9: 32506.559 | G9: 4856.3573 | H9: 7105.3528 | I9: 44186.459 | J9: 11006.648 | K9: 35984.637 | L9: 40695.915 | M9: 22044.871 | N9: 24305.883 | O9: 7120.6486 | Q9: 33792.866 | R9: 33308.55 | S9: 12462.651 | T9: 30229.995 | V9: 4577.148 | W9: 31513.423 | X9: 39717.144 | Y9: 6631.6443 | Z9: 12668.507 | AA9: 24075.09 | AB9: 249678.14 | AC9: 35554.1 | AD9: 62421.225 | AE9: 39388.574 | AF9: 91856.869 | AG9: 34805.041 | AH9: 599.532 | AI9: 42824.197 | AJ9: 20028.787 | AK9: 29627.32 | AL9: 1065574.1
A10: Abuja | D10: Japan | E10: 21196.913 | G10: 20606.464 | I10: 82602.55 | J10: 34082.865 | K10: 38506.529 | L10: 18641.222 | N10: 15253.07 | O10: 7955.6342 | Q10: 67110.666 | R10: 15705.464 | S10: 32142.114 | T10: 23449.834 | U10: 9315.4974 | V10: 4603.0824 | W10: 68665.574 | X10: 11984.891 | Y10: 31024.839 | AA10: 49818.787 | AB10: 9062.3469 | AC10: 14287.896 | AD10: 63856.507 | AE10: 14268.608 | AG10: 14527.748 | AH10: 29808.425 | AI10: 31130.742 | AJ10: 50582.706 | AK10: 74882.386 | AL10: 855073.36
A11: Lagos | D11: Kenya | E11: 11003.767 | F11: 24447.959 | G11: 17731.623 | H11: 667.74 | I11: 3823.6152 | J11: 15174.426 | K11: 16061.973 | M11: 3115.3609 | N11: 66852.129 | O11: 15860.782 | P11: 47962.718 | R11: 52609.066 | S11: 47047.518 | T11: 27763.018 | U11: 17867.219 | V11: 3799.8031 | W11: 181608.7 | Y11: 70602.928 | Z11: 4866.3288 | AA11: 13669.81 | AB11: 10946.712 | AC11: 13108.786 | AD11: 4569.8508 | AF11: 123535.74 | AG11: 38264.51 | AH11: 51457.54 | AI11: 1030.7574 | AJ11: 52863.981 | AK11: 9050.5053 | AL11: 947364.87
A12: Port Harcourt | D12: Nigeria | E12: 32280.325 | F12: 48850.807 | G12: 40139.875 | H12: 24833.098 | J12: 49501.66 | K12: 27158.894 | L12: 12967.959 | M12: 4737.2198 | O12: 23687.576 | P12: 685.06776 | S12: 112088.82 | U12: 119970.85 | V12: 7135.57 | W12: 15009.057 | X12: 55110.62 | Z12: 28041.025 | AA12: 52727.976 | AB12: 43539.233 | AC12: 68626.652 | AD12: 1010.3759 | AG12: 10786.321 | AH12: 100069.72 | AJ12: 2879.9836 | AL12: 881838.68
A13: South Africa | D13: South Africa | F13: 20171.633 | G13: 1886.9916 | H13: 58520.37 | I13: 27331.83 | K13: 79406.785 | M13: 86597.081 | P13: 3116.21 | Q13: 54214.972 | R13: 6576.299 | S13: 78566.393 | U13: 76636.156 | W13: 39907.476 | X13: 88311.187 | Y13: 29618.551 | Z13: 4826.5396 | AA13: 5565.3273 | AB13: 15476.944 | AC13: 14032.851 | AD13: 31556.188 | AE13: 12954.358 | AG13: 434.45248 | AH13: 18061.204 | AJ13: 12972.002 | AK13: 13185.543 | AL13: 779927.34
A14: Cape Town | D14: United Kingdom | E14: 66551.125 | F14: 20646.611 | G14: 96832.738 | H14: 31801.901 | I14: 23687.524 | J14: 853.32277 | L14: 61319.075 | M14: 4132.0325 | O14: 35720.318 | P14: 27965.367 | Q14: 27424.45 | R14: 11332.143 | S14: 48616.566 | U14: 62736.309 | V14: 29905.538 | W14: 65319.42 | X14: 52414.751 | Y14: 16013.682 | Z14: 33938.143 | AA14: 21062.612 | AB14: 19800.889 | AC14: 114279.15 | AD14: 39263.703 | AE14: 5610.0924 | AF14: 44605.989 | AG14: 26003.218 | AH14: 91431.438 | AJ14: 25249.613 | AK14: 8764.4066 | AL14: 1113282.1
A15: Durban | D15: USA | E15: 11375.258 | G15: 38240.697 | H15: 25299.04 | I15: 97443.478 | J15: 27401.728 | L15: 12031.492 | M15: 68738.647 | N15: 52311.008 | O15: 9984.7161 | P15: 31035.218 | Q15: 18566.16 | R15: 4654.7743 | S15: 32086.376 | T15: 25483.915 | V15: 71887.464 | Z15: 108770.28 | AB15: 27431.638 | AC15: 53872.641 | AD15: 3644.3213 | AG15: 5533.623 | AH15: 16023.123 | AI15: 14692.623 | AJ15: 12186.369 | AL15: 768694.59
A16: Johannesburg | D16: Grand Total | E16: 371604.58 | F16: 239506.83 | G16: 336135.17 | H16: 339044.67 | I16: 384156.19 | J16: 366808.72 | K16: 382101.37 | L16: 354378.94 | M16: 433788.64 | N16: 307793.71 | O16: 221608.5 | P16: 151883.45 | Q16: 299100.37 | R16: 223498.2 | S16: 560860.56 | T16: 275628.62 | U16: 486970.83 | V16: 236474.06 | W16: 634490.72 | X16: 382009.38 | Y16: 215576.67 | Z16: 374300.11 | AA16: 209425.99 | AB16: 470192.17 | AC16: 416985.77 | AD16: 375723.96 | AE16: 127009.51 | AF16: 416944.19 | AG16: 246114.84 | AH16: 417732.48 | AI16: 141266.51 | AJ16: 347613.19 | AK16: 172279.73 | AL16: 10919009
A17: Americas
A18: Brazil | AD18: Salesperson productivity
A19: Brasília | AD19: Row Labels | AE19: Count of OrderID | AF19: Average of GrossProfit | AG19: Sum of GrossRevenue
A20: Rio de Janeiro | AD20: A. Patel | AE20: 46 | AF20: 6135.5277 | AG20: 877449.32
A21: São Paulo | AD21: B. Chen | AE21: 47 | AF21: 6824.7486 | AG21: 866976.37
A22: Canada | AD22: C. Otieno | AE22: 37 | AF22: 6225.9331 | AG22: 689776.36
A23: Montreal | AD23: D. Smith | AE23: 38 | AF23: 3975.7087 | AG23: 576820.19
A24: Ottawa | AD24: E. Garcia | AE24: 34 | AF24: 6028.863 | AG24: 543846.44
A25: Toronto | AD25: F. Müller | AE25: 51 | AF25: 4935.9414 | AG25: 812637.17
A26: Vancouver | AD26: G. Dubois | AE26: 30 | AF26: 5748.0624 | AG26: 510653.71
A27: USA | AD27: H. Kim | AE27: 45 | AF27: 3070.0625 | AG27: 698700.3
A28: Austin | AD28: I. Johnson | AE28: 38 | AF28: 3684.7814 | AG28: 541165.67
A29: Chicago | AD29: J. Njeri | AE29: 50 | AF29: 5462.2622 | AG29: 802384.66
A30: New York | AD30: K. Singh | AE30: 44 | AF30: 6335.5061 | AG30: 883348.13
A31: San Francisco | AD31: L. Okafor | AE31: 46 | AF31: 5872.9289 | AG31: 853476.7
... A36: Shenzhen | AD36: Grand Total | AE36: 631 | AF36: 5424.427 | AG36: 10919009
A37: India
A38: Bengaluru
A39: Delhi
A40: Hyderabad
A41: Mumbai
A42: Japan
A43: Nagoya
A44: Osaka
A45: Tokyo
A46: Europe
A47: France
A48: Lyon
... A70: revenue by product category and SKUs
A71: Row Labels | B71: Sum of GrossRevenue
A72: Accessories | B72: 1315287.3
A73: ACC-6626 | B73: 79082.507
A74: ACC-2988 | B74: 53034.364
A75: ACC-9283 | B75: 46450.26
A76: ACC-9533 | B76: 43084.872
A77: ACC-8098 | B77: 38096.184
A78: ACC-4490 | B78: 35396.278
A79: ACC-7838 | B79: 35167.745
A80: ACC-5177 | B80: 34139.16
A81: ACC-9162 | B81: 33062.236
A82: ACC-7078 | B82: 32086.376
A83: ACC-1375 | B83: 31513.085
... A708: Grand Total | B708: 10919009

Sheet Pivot 2
A1: Salesperson productivity
A2: Row Labels | B2: Count of OrderID | C2: Sum of GrossRevenue | D2: Sum of GrossProfit | E2: Revenue per Order | F2: Gross Profit per Order | G2: Orders per Month
A3: A. Patel | B3: 46 | C3: 877449.32 | D3: 282234.27 | E3: =IF(B5=0,"",C5/B5) -> 18642.604 | F3: =IF(B3=0,"",D3/B3) -> 6135.5277 | G3: =B3/33 -> 1.3939394
A4: B. Chen | B4: 47 | C4: 866976.37 | D4: 320763.18 | E4: =IF(B6=0,"",C6/B6) -> 15179.479 | F4: =IF(B4=0,"",D4/B4) -> 6824.7486 | G4: =B4/33 -> 1.4242424
A5: C. Otieno | B5: 37 | C5: 689776.36 | D5: 230359.52 | E5: =IF(B7=0,"",C7/B7) -> 15995.484 | F5: =IF(B5=0,"",D5/B5) -> 6225.9331 | G5: =B5/33 -> 1.1212121
A6: D. Smith | B6: 38 | C6: 576820.19 | D6: 151076.93 | E6: =IF(B8=0,"",C8/B8) -> 15934.062 | F6: =IF(B6=0,"",D6/B6) -> 3975.7087 | G6: =B6/33 -> 1.1515152
A7: E. Garcia | B7: 34 | C7: 543846.44 | D7: 204981.34 | E7: =IF(B9=0,"",C9/B9) -> 17021.79 | F7: =IF(B7=0,"",D7/B7) -> 6028.863 | G7: =B7/33 -> 1.030303
A8: F. Müller | B8: 51 | C8: 812637.17 | D8: 251733.01 | E8: =IF(B10=0,"",C10/B10) -> 15526.673 | F8: =IF(B8=0,"",D8/B8) -> 4935.9414 | G8: =B8/33 -> 1.5454545
A9: G. Dubois | B9: 30 | C9: 510653.71 | D9: 172441.87 | E9: =IF(B11=0,"",C11/B11) -> 14241.202 | F9: =IF(B9=0,"",D9/B9) -> 5748.0624 | G9: =B9/33 -> 0.90909091
A10: H. Kim | B10: 45 | C10: 698700.3 | D10: 138152.81 | E10: =IF(B12=0,"",C12/B12) -> 16047.693 | F10: =IF(B10=0,"",D10/B10) -> 3070.0625 | G10: =B10/33 -> 1.3636364
A11: I. Johnson | B11: 38 | C11: 541165.67 | D11: 140021.69 | E11: =IF(B13=0,"",C13/B13) -> 20076.094 | F11: =IF(B11=0,"",D11/B11) -> 3684.7814 | G11: =B11/33 -> 1.1515152
A12: J. Njeri | B12: 50 | C12: 802384.66 | D12: 273113.11 | E12: =IF(B14=0,"",C14/B14) -> 18553.841 | F12: =IF(B12=0,"",D12/B12) -> 5462.2622 | G12: =B12/33 -> 1.5151515
A13: K. Singh | B13: 44 | C13: 883348.13 | D13: 278762.27 | E13: =IF(B15=0,"",C15/B15) -> 20347.848 | F13: =IF(B13=0,"",D13/B13) -> 6335.5061 | G13: =B13/33 -> 1.3333333
A14: L. Okafor | B14: 46 | C14: 853476.7 | D14: 270154.73 | E14: =IF(B16=0,"",C16/B16) -> 12135.161 | F14: =IF(B14=0,"",D14/B14) -> 5872.9289 | G14: =B14/33 -> 1.3939394
... A17: O. Wang | B17: 37 | C17: 647724.9 | D17: 185219.44 | E17: =IF(B19=0,"",C19/B19) -> 17304.293 | F17: =IF(B17=0,"",D17/B17) -> 5005.9307 | G17: =B17/33 -> 1.1212121
A18: Unassigned | B18: 8 | C18: 249026.85 | D18: 100098 | E18: =IF(B20=0,"",C20/B20)
A19: Grand Total | B19: 631 | C19: 10919009 | D19: 3422813.4 | E19: =IF(B21=0,"",C21/B21)
A23: Revenue/Order | B23: Who sells high-value deals
A24: GP/Order | B24: Who sells profitably
A25: Orders/Month | B25: Who is most active
A27: Channel mix
A28: Sum of GrossRevenue | B28: Column Labels
A29: Row Labels | B29: Direct | C29: Distributor | D29: Marketplace | E29: Not Provided | F29: Online | G29: Retail | H29: Grand Total
A30: Africa | B30: 0.1771611 | C30: 0.24321571 | D30: 0.20216229 | E30: 0.012539396 | F30: 0.16611138 | G30: 0.19881012 | H30: 1 | I30: In Africa, Disributor dominates
A31: Americas | B31: 0.27959653 | C31: 0.21153723 | D31: 0.13624034 | E31: 0.003441983 | F31: 0.25656496 | G31: 0.11261896 | H31: 1 | I31: In America Direct channel dominates
A32: Asia | B32: 0.23912684 | C32: 0.18066408 | D32: 0.19367519 | E32: 0.0034990619 | F32: 0.146704 | G32: 0.23633082 | H32: 1 | I32: In Asia, Direct dominates
A33: Europe | B33: 0.30082759 | C33: 0.11379438 | D33: 0.20810337 | E33: 0.0017250865 | F33: 0.20900009 | G33: 0.16654949 | H33: 1 | I33: Direct dominates
A34: Grand Total | B34: 0.25011474 | C34: 0.18606089 | D34: 0.18525904 | E34: 0.0051901526 | F34: 0.194379 | G34: 0.17899617 | H34: 1
A41: cannibalization
A42: Sum of GrossRevenue | B42: Column Labels
B43: 2023 | C43: 2024 | D43: 2025 | E43: Grand Total
A47: Row Labels
A48: Africa | B48: 0.33667896 | C48: 0.39027996 | D48: 0.27304108 | E48: 1
A49: Americas | B49: 0.34022146 | C49: 0.39390739 | D49: 0.26587115 | E49: 1
A50: Asia | B50: 0.34292094 | C50: 0.41392727 | D50: 0.24315179 | E50: 1
A51: Europe | B51: 0.32689298 | C51: 0.43695194 | D51: 0.23615507 | E51: 1
A52: Grand Total | B52: 0.336653 | C52: 0.40925246 | D52: 0.25409454 | E52: 1

Sheet Cohort Analysis
B2: Row Labels | C2: Min of Months
B3: Brazil | C3: 44927
B4: Canada | C4: 44927
B5: China | C5: 44927
B6: France | C6: 44927
B7: Germany | C7: 44927
B8: India | C8: 44958
B9: Japan | C9: 44986
B10: Kenya | C10: 44927
B11: Nigeria | C11: 44927
B12: South Africa | C12: 44927
B13: United Kingdom | C13: 44927
B14: USA | C14: 44927
B15: Grand Total | C15: 44927

Sheet ABC analysis
A3: ProductCategory | B3: SKU | C3: Sum of GrossRevenue | F3: ProductCategory | G3: SKU | H3: Sum of GrossRevenue | I3: Category totals | J3: % share | K3: Cumulative | L3: ABC Classification
A4: Networking | B4: NET-2365 | C4: 109244 | F4: Components | G4: CMP-8851 | H4: 139277.83 | I4: =SUMIF(F4:F632, F4, H4:H632) -> 1550200.5 | J4: =H4/I4 -> 0.089845041 | K4: =IF(F4=F3, K3+J4, J4) -> 0.089845041 | L4: =IF(K4<=0.8,"A", IF(K4<=0.95,"B","C")) -> A
A5: Networking | B5: NET-5987 | C5: 82141.34 | F5: Networking | G5: NET-2365 | H5: 109244 | I5: =SUMIF(F5:F633, F5, H5:H633) -> 1774683.1 | J5: =H5/I5 -> 0.061556906 | K5: =IF(F5=F4, K4+J5, J5) -> 0.061556906 | L5: =IF(K5<=0.8,"A", IF(K5<=0.95,"B","C")) -> A
A6: Networking | B6: NET-5523 | C6: 79548.756 | F6: Laptops | G6: LAP-8910 | H6: 102122.94 | I6: =SUMIF(F6:F634, F6, H6:H634) -> 1711094.4 | J6: =H6/I6 -> 0.059682823 | K6: =IF(F6=F5, K5+J6, J6) -> 0.059682823 | L6: =IF(K6<=0.8,"A", IF(K6<=0.95,"B","C")) -> A
A7: Networking | B7: NET-1612 | C7: 66988.771 | F7: Monitors | G7: MON-6962 | H7: 92715.25 | I7: =SUMIF(F7:F635, F7, H7:H635) -> 1551590.9 | J7: =H7/I7 -> 0.059754959 | K7: =IF(F7=F6, K6+J7, J7) -> 0.059754959 | L7: =IF(K7<=0.8,"A", IF(K7<=0.95,"B","C")) -> A
A8: Networking | B8: NET-5018 | C8: 60292.805 | F8: Monitors | G8: MON-2266 | H8: 87404.93 | I8: =SUMIF(F8:F636, F8, H8:H636) -> 1458875.6 | J8: =H8/I8 -> 0.05991253 | K8: =IF(F8=F7, K7+J8, J8) -> 0.11966749 | L8: =IF(K8<=0.8,"A", IF(K8<=0.95,"B","C")) -> A
A9: Networking | B9: NET-1282 | C9: 51768.182 | F9: Monitors | G9: MON-6699 | H9: 85637.74 | I9: =SUMIF(F9:F637, F9, H9:H637) -> 1371470.7 | J9: =H9/I9 -> 0.062442268 | K9: =IF(F9=F8, K8+J9, J9) -> 0.18210976 | L9: =IF(K9<=0.8,"A", IF(K9<=0.95,"B","C")) -> A
A10: Networking | B10: NET-4735 | C10: 50090.397 | F10: Components | G10: CMP-3938 | H10: 84136.12 | I10: =SUMIF(F10:F638, F10, H10:H638) -> 1410922.7 | J10: =H10/I10 -> 0.059631984 | K10: =IF(F10=F9, K9+J10, J10) -> 0.059631984 | L10: =IF(K10<=0.8,"A", IF(K10<=0.95,"B","C")) -> A
A11: Networking | B11: NET-3850 | C11: 49336.511 | F11: Laptops | G11: LAP-3904 | H11: 82514.712 | I11: =SUMIF(F11:F639, F11, H11:H639) -> 1608971.4 | J11: =H11/I11 -> 0.051284137 | K11: =IF(F11=F10, K10+J11, J11) -> 0.051284137 | L11: =IF(K11<=0.8,"A", IF(K11<=0.95,"B","C")) -> A
A12: Networking | B12: NET-6036 | C12: 47962.718 | F12: Networking | G12: NET-5987 | H12: 82141.34 | I12: =SUMIF(F12:F640, F12, H12:H640) -> 1665439.1 | J12: =H12/I12 -> 0.049321131 | K12: =IF(F12=F11, K11+J12, J12) -> 0.049321131 | L12: =IF(K12<=0.8,"A", IF(K12<=0.95,"B","C")) -> A
A13: Networking | B13: NET-3828 | C13: 47693.373 | F13: Networking | G13: NET-5523 | H13: 79548.756 | I13: =SUMIF(F13:F641, F13, H13:H641) -> 1583297.7 | J13: =H13/I13 -> 0.050242449 | K13: =IF(F13=F12, K12+J13, J13) -> 0.09956358 | L13: =IF(K13<=0.8,"A", IF(K13<=0.95,"B","C")) -> A
A14: Networking | B14: NET-3535 | C14: 43553.493 | F14: Accessories | G14: ACC-6626 | H14: 79082.507 | I14: =SUMIF(F14:F642, F14, H14:H642) -> 1315287.3 | J14: =H14/I14 -> 0.060125651 | K14: =IF(F14=F13, K13+J14, J14) -> 0.060125651 | L14: =IF(K14<=0.8,"A", IF(K14<=0.95,"B","C")) -> A
A15: Networking | B15: NET-1893 | C15: 40488.793 | F15: Monitors | G15: MON-5188 | H15: 72665.817 | I15: =SUMIF(F15:F643, F15, H15:H643) -> 1285833 | J15: =H15/I15 -> 0.056512642 | K15: =IF(F15=F14, K14+J15, J15) -> 0.056512642 | L15: =IF(K15<=0.8,"A", IF(K15<=0.95,"B","C")) -> A
... A632: Accessories | B632: ACC-6777 | C632: 18.65984 | F632: Accessories | G632: ACC-6777 | H632: 18.65984 | I632: =SUMIF(F632:F1260, F632, H632:H1260) -> 18.65984 | J632: =H632/I632 -> 1 | K632: =IF(F632=F631, K631+J632, J632) -> 1 | L632: =IF(K632<=0.8,"A", IF(K632<=0.95,"B","C")) -> C

Sheet Scenario Summary
B2: Scenario Summary
D3: Current Values: | E3: Original | F3: Worst Case - High Inflation | G3: Best Case
E4: Created by Hp on 1/27/2026 | F4: Created by Hp on 1/27/2026 | G4: Created by Hp on 1/27/2026
B5: Changing Cells:
C6: Global_Discount_Cap | D6: 0.1 | E6: 0.1 | F6: 0.25 | G6: 0.05
C7: Unit_Cost_Inflation | D7: 0.05 | E7: 0.05 | F7: 0.15 | G7: 0.02
C8: Quantity_Uplift | D8: 0.1 | E8: 0.08 | F8: 0 | G8: 0.15
B10: Notes: Current Values column represents values of changing cells at
B11: time Scenario Summary Report was created. Changing cells for each
B12: scenario are highlighted in gray.

Sheet What-If Analysis
A2: INPUTS
A3: Label | B3: Value
A4: Global Discount Cap | B4: 0.1
A5: Inflation | B5: 0.05
A6: Quantity Uplift | B6: 0.1
A9: SCENARIO COLUMNS
A10: Scenario Quantity | B10: Scenario Unit Cost | C10: Applied discount

Sheet Pivot
A4: Revenue by Month
A5: Row Labels | B5: Sum of GrossRevenue
A6: 2023 | B6: 3675917
A7: Jan | B7: 151883.45
A8: Feb | B8: 433788.64
A9: Mar | B9: 215576.67
A10: Apr | B10: 371604.58
A11: May | B11: 470192.17
A12: Jun | B12: 236474.06
A13: Jul | B13: 560860.56
A14: Aug | B14: 339044.67
A15: Sep | B15: 141266.51
A16: Oct | B16: 246114.84
A17: Nov | B17: 127009.51
... A42: Grand Total | B42: 10919009
A56: Count of OrderID | B56: Sum of GrossRevenue | D56: Order Count | E56: Total Revenue
A57: 631 | B57: 10919009 | D57: =GETPIVOTDATA("Count of OrderID",$A$56) -> 631 | E57: =GETPIVOTDATA("Sum of GrossRevenue",$A$63) -> 10919009
D60: AOV | E60: =E57/D57 -> 17304.293
A63: Sum of GrossProfit | B63: Sum of GrossRevenue | D63: Total Profit | E63: Total Revenue
A64: 3422813.4 | B64: 10919009 | D64: =GETPIVOTDATA("Sum of GrossProfit",$A$63) -> 3422813.4 | E64: =GETPIVOTDATA("Sum of GrossRevenue",$A$63) -> 10919009
D66: Margin % | E66: =D64/E64 -> 0.31347291
A70: On-Time %
A71: 0.2725832
A74: Profit by Region and Channel
A75: Sum of GrossProfit | B75: Column Labels
A76: Row Labels | B76: Direct | C76: Distributor | D76: Marketplace | E76: Not Provided | F76: Online | G76: Retail | H76: Grand Total
A77: Africa | B77: 178727.35 | C77: 202729.86 | D77: 164839.3 | E77: 16237.344 | F77: 145453.95 | G77: 141171.08 | H77: 849158.9
A78: Americas | B78: 258674.93 | C78: 175736.86 | D78: 96609.648 | E78: 777.96 | F78: 261943.84 | G78: 69035.709 | H78: 862778.95
A79: Asia | B79: 246072.37 | C79: 151146.75 | D79: 132709.51 | E79: 4017.1205 | F79: 149042.39 | G79: 158051.77 | H79: 841039.91
A80: Europe | B80: 292716.95 | C80: 105550.85 | D80: 118458.01 | E80: 1263.5065 | F80: 200067.16 | G80: 151779.17 | H80: 869835.66
A81: Grand Total | B81: 976191.6 | C81: 635164.32 | D81: 512616.48 | E81: 22295.931 | F81: 756507.34 | G81: 520037.74 | H81: 3422813.4
A87: SKUs by Revenue
A89: Row Labels | B89: Sum of GrossRevenue
A90: NET-5523 | B90: 79548.756
A91: NET-5987 | B91: 82141.34
A92: LAP-3904 | B92: 82514.712
A93: CMP-3938 | B93: 84136.12
A94: MON-6699 | B94: 85637.74
A95: MON-2266 | B95: 87404.93
A96: MON-6962 | B96: 92715.25
A97: LAP-8910 | B97: 102122.94
A98: NET-2365 | B98: 109244
A99: CMP-8851 | B99: 139277.83
A100: Grand Total | B100: 944743.62
A106: Price Compliance
A107: Region | B107: Salesperson | C107: Total Orders | D107: Sum of High Discount Flag | E107: % Share of Non-Compliant
A108: Africa | B108: A. Patel | C108: 16 | D108: 3 | E108: =GETPIVOTDATA("Sum of High Discount Flag",$A$107,"Region","Africa","Salesperson","A. Patel")/GETPIVOTDATA("Total Orders",$A$107,"Region","Africa","Salesperson","A. Patel") -> 0.1875
B109: B. Chen | C109: 8 | D109: 0 | E109: =GETPIVOTDATA("Sum of High Discount Flag",$A$107,"Region","Africa","Salesperson","B. Chen")/GETPIVOTDATA("Total Orders",$A$107,"Region","Africa","Salesperson","B. Chen") -> 0
B110: C. Otieno | C110: 8 | D110: 2 | E110: =GETPIVOTDATA("Sum of High Discount Flag",$A$107,"Region","Africa","Salesperson","C. Otieno")/GETPIVOTDATA("Total Orders",$A$107,"Region","Africa","Salesperson","C. Otieno") -> 0.25
B111: D. Smith | C111: 10 | D111: 2 | E111: =GETPIVOTDATA("Sum of High Discount Flag",$A$107,"Region","Africa","Salesperson","D. Smith")/GETPIVOTDATA("Total Orders",$A$107,"Region","Africa","Salesperson","D. Smith") -> 0.2
B112: E. Garcia | C112: 5 | D112: 1 | E112: =GETPIVOTDATA("Sum of High Discount Flag",$A$107,"Region","Africa","Salesperson","E. Garcia")/GETPIVOTDATA("Total Orders",$A$107,"Region","Africa","Salesperson","E. Garcia") -> 0.2 | F112: % of Non-Compliant Orders
B113: F. Müller | C113: 13 | D113: 0 | E113: =GETPIVOTDATA("Sum of High Discount Flag",$A$107,"Region","Africa","Salesperson","F. Müller")/GETPIVOTDATA("Total Orders",$A$107,"Region","Africa","Salesperson","F. Müller") -> 0
B114: G. Dubois | C114: 3 | D114: 0 | E114: =GETPIVOTDATA("Sum of High Discount Flag",$A$107,"Region","Africa","Salesperson","G. Dubois")/GETPIVOTDATA("Total Orders",$A$107,"Region","Africa","Salesperson","G. Dubois") -> 0
B115: H. Kim | C115: 7 | D115: 1 | E115: =GETPIVOTDATA("Sum of High Discount Flag",$A$107,"Region","Africa","Salesperson","H. Kim")/GETPIVOTDATA("Total Orders",$A$107,"Region","Africa","Salesperson","H. Kim") -> 0.14285714
B116: I. Johnson | C116: 8 | D116: 2 | E116: =GETPIVOTDATA("Sum of High Discount Flag",$A$107,"Region","Africa","Salesperson","I. Johnson")/GETPIVOTDATA("Total Orders",$A$107,"Region","Africa","Salesperson","I. Johnson") -> 0.25
B117: J. Njeri | C117: 12 | D117: 3 | E117: =GETPIVOTDATA("Sum of High Discount Flag",$A$107,"Region","Africa","Salesperson","J. Njeri")/GETPIVOTDATA("Total Orders",$A$107,"Region","Africa","Salesperson","J. Njeri") -> 0.25
B118: K. Singh | C118: 14 | D118: 0 | E118: =GETPIVOTDATA("Sum of High Discount Flag",$A$107,"Region","Africa","Salesperson","K. Singh")/GETPIVOTDATA("Total Orders",$A$107,"Region","Africa","Salesperson","K. Singh") -> 0
B119: L. Okafor | C119: 10 | D119: 2 | E119: =GETPIVOTDATA("Sum of High Discount Flag",$A$107,"Region","Africa","Salesperson","L. Okafor")/GETPIVOTDATA("Total Orders",$A$107,"Region","Africa","Salesperson","L. Okafor") -> 0.2
B120: M. Rossi | C120: 16 | D120: 5 | E120: =GETPIVOTDATA("Sum of High Discount Flag",$A$107,"Region","Africa","Salesperson","M. Rossi")/GETPIVOTDATA("Total Orders",$A$107,"Region","Africa","Salesperson","M. Rossi") -> 0.3125
B121: N. Brown | C121: 4 | D121: 0 | E121: =GETPIVOTDATA("Sum of High Discount Flag",$A$107,"Region","Africa","Salesperson","N. Brown")/GETPIVOTDATA("Total Orders",$A$107,"Region","Africa","Salesperson","N. Brown") -> 0
B122: O. Wang | C122: 9 | D122: 0 | E122: =GETPIVOTDATA("Sum of High Discount Flag",$A$107,"Region","Africa","Salesperson","O. Wang")/GETPIVOTDATA("Total Orders",$A$107,"Region","Africa","Salesperson","O. Wang") -> 0
B123: Unassigned | C123: 2 | D123: 1 | E123: =GETPIVOTDATA("Sum of High Discount Flag",$A$107,"Region","Africa","Salesperson","Unassigned")/GETPIVOTDATA("Total Orders",$A$107,"Region","Africa","Salesperson","Unassigned") -> 0.5
A124: Americas | B124: A. Patel | C124: 10 | D124: 5 | E124: =GETPIVOTDATA("Sum of High Discount Flag",$A$107,"Region","Americas","Salesperson","A. Patel")/GETPIVOTDATA("Total Orders",$A$107,"Region","Americas","Salesperson","A. Patel") -> 0.5
B125: B. Chen | C125: 8 | D125: 1 | E125: =GETPIVOTDATA("Sum of High Discount Flag",$A$107,"Region","Americas","Salesperson","B. Chen")/GETPIVOTDATA("Total Orders",$A$107,"Region","Americas","Salesperson","B. Chen") -> 0.125
B126: C. Otieno | C126: 14 | D126: 2 | E126: =GETPIVOTDATA("Sum of High Discount Flag",$A$107,"Region","Americas","Salesperson","C. Otieno")/GETPIVOTDATA("Total Orders",$A$107,"Region","Americas","Salesperson","C. Otieno") -> 0.14285714
B127: D. Smith | C127: 8 | D127: 4 | E127: =GETPIVOTDATA("Sum of High Discount Flag",$A$107,"Region","Americas","Salesperson","D. Smith")/GETPIVOTDATA("Total Orders",$A$107,"Region","Americas","Salesperson","D. Smith") -> 0.5
B128: E. Garcia | C128: 5 | D128: 0 | E128: =GETPIVOTDATA("Sum of High Discount Flag",$A$107,"Region","Americas","Salesperson","E. Garcia")/GETPIVOTDATA("Total Orders",$A$107,"Region","Americas","Salesperson","E. Garcia") -> 0
B129: F. Müller | C129: 15 | D129: 1 | E129: =GETPIVOTDATA("Sum of High Discount Flag",$A$107,"Region","Americas","Salesperson","F. Müller")/GETPIVOTDATA("Total Orders",$A$107,"Region","Americas","Salesperson","F. Müller") -> 0.066666667
B130: G. Dubois | C130: 8 | D130: 1 | E130: =GETPIVOTDATA("Sum of High Discount Flag",$A$107,"Region","Americas","Salesperson","G. Dubois")/GETPIVOTDATA("Total Orders",$A$107,"Region","Americas","Salesperson","G. Dubois") -> 0.125
B131: H. Kim | C131: 9 | D131: 0 | E131: =GETPIVOTDATA("Sum of High Discount Flag",$A$107,"Region","Americas","Salesperson","H. Kim")/GETPIVOTDATA("Total Orders",$A$107,"Region","Americas","Salesperson","H. Kim") -> 0
B132: I. Johnson | C132: 14 | D132: 5 | E132: =GETPIVOTDATA("Sum of High Discount Flag",$A$107,"Region","Americas","Salesperson","I. Johnson")/GETPIVOTDATA("Total Orders",$A$107,"Region","Americas","Salesperson","I. Johnson") -> 0.35714286
B133: J. Njeri | C133: 10 | D133: 0 | E133: =GETPIVOTDATA("Sum of High Discount Flag",$A$107,"Region","Americas","Salesperson","J. Njeri")/GETPIVOTDATA("Total Orders",$A$107,"Region","Americas","Salesperson","J. Njeri") -> 0
B134: K. Singh | C134: 10 | D134: 1 | E134: =GETPIVOTDATA("Sum of High Discount Flag",$A$107,"Region","Americas","Salesperson","K. Singh")/GETPIVOTDATA("Total Orders",$A$107,"Region","Americas","Salesperson","K. Singh") -> 0.1
B135: L. Okafor | C135: 12 | D135: 3 | E135: =GETPIVOTDATA("Sum of High Discount Flag",$A$107,"Region","Americas","Salesperson","L. Okafor")/GETPIVOTDATA("Total Orders",$A$107,"Region","Americas","Salesperson","L. Okafor") -> 0.25
B136: M. Rossi | C136: 12 | D136: 2 | E136: =GETPIVOTDATA("Sum of High Discount Flag",$A$107,"Region","Americas","Salesperson","M. Rossi")/GETPIVOTDATA("Total Orders",$A$107,"Region","Americas","Salesperson","M. Rossi") -> 0.16666667
B137: N. Brown | C137: 7 | D137: 1 | E137: =GETPIVOTDATA("Sum of High Discount Flag",$A$107,"Region","Americas","Salesperson","N. Brown")/GETPIVOTDATA("Total Orders",$A$107,"Region","Americas","Salesperson","N. Brown") -> 0.14285714
B138: O. Wang | C138: 12 | D138: 0 | E138: =GETPIVOTDATA("Sum of High Discount Flag",$A$107,"Region","Americas","Salesperson","O. Wang")/GETPIVOTDATA("Total Orders",$A$107,"Region","Americas","Salesperson","O. Wang") -> 0
B139: Unassigned | C139: 3 | D139: 1 | E139: =GETPIVOTDATA("Sum of High Discount Flag",$A$107,"Region","Americas","Salesperson","Unassigned")/GETPIVOTDATA("Total Orders",$A$107,"Region","Americas","Salesperson","Unassigned") -> 0.33333333
A140: Asia | B140: A. Patel | C140: 10 | D140: 0 | E140: =GETPIVOTDATA("Sum of High Discount Flag",$A$107,"Region","Asia","Salesperson","A. Patel")/GETPIVOTDATA("Total Orders",$A$107,"Region","Asia","Salesperson","A. Patel") -> 0
B141: B. Chen | C141: 16 | D141: 1 | E141: =GETPIVOTDATA("Sum of High Discount Flag",$A$107,"Region","Asia","Salesperson","B. Chen")/GETPIVOTDATA("Total Orders",$A$107,"Region","Asia","Salesperson","B. Chen") -> 0.0625
B142: C. Otieno | C142: 10 | D142: 3 | E142: =GETPIVOTDATA("Sum of High Discount Flag",$A$107,"Region","Asia","Salesperson","C. Otieno")/GETPIVOTDATA("Total Orders",$A$107,"Region","Asia","Salesperson","C. Otieno") -> 0.3
B143: D. Smith | C143: 9 | D143: 1 | E143: =GETPIVOTDATA("Sum of High Discount Flag",$A$107,"Region","Asia","Salesperson","D. Smith")/GETPIVOTDATA("Total Orders",$A$107,"Region","Asia","Salesperson","D. Smith") -> 0.11111111
B144: E. Garcia | C144: 8 | D144: 0 | E144: =GETPIVOTDATA("Sum of High Discount Flag",$A$107,"Region","Asia","Salesperson","E. Garcia")/GETPIVOTDATA("Total Orders",$A$107,"Region","Asia","Salesperson","E. Garcia") -> 0
B145: F. Müller | C145: 12 | D145: 3 | E145: =GETPIVOTDATA("Sum of High Discount Flag",$A$107,"Region","Asia","Salesperson","F. Müller")/GETPIVOTDATA("Total Orders",$A$107,"Region","Asia","Salesperson","F. Müller") -> 0.25
B146: G. Dubois | C146: 11 | D146: 1 | E146: =GETPIVOTDATA("Sum of High Discount Flag",$A$107,"Region","Asia","Salesperson","G. Dubois")/GETPIVOTDATA("Total Orders",$A$107,"Region","Asia","Salesperson","G. Dubois") -> 0.090909091
B147: H. Kim | C147: 16 | D147: 2 | E147: =GETPIVOTDATA("Sum of High Discount Flag",$A$107,"Region","Asia","Salesperson","H. Kim")/GETPIVOTDATA("Total Orders",$A$107,"Region","Asia","Salesperson","H. Kim") -> 0.125
B148: I. Johnson | C148: 8 | D148: 1 | E148: =GETPIVOTDATA("Sum of High Discount Flag",$A$107,"Region","Asia","Salesperson","I. Johnson")/GETPIVOTDATA("Total Orders",$A$107,"Region","Asia","Salesperson","I. Johnson") -> 0.125
B149: J. Njeri | C149: 19 | D149: 2 | E149: =GETPIVOTDATA("Sum of High Discount Flag",$A$107,"Region","Asia","Salesperson","J. Njeri")/GETPIVOTDATA("Total Orders",$A$107,"Region","Asia","Salesperson","J. Njeri") -> 0.10526316
B150: K. Singh | C150: 7 | D150: 1 | E150: =GETPIVOTDATA("Sum of High Discount Flag",$A$107,"Region","Asia","Salesperson","K. Singh")/GETPIVOTDATA("Total Orders",$A$107,"Region","Asia","Salesperson","K. Singh") -> 0.14285714
B151: L. Okafor | C151: 14 | D151: 3 | E151: =GETPIVOTDATA("Sum of High Discount Flag",$A$107,"Region","Asia","Salesperson","L. Okafor")/GETPIVOTDATA("Total Orders",$A$107,"Region","Asia","Salesperson","L. Okafor") -> 0.21428571
B152: M. Rossi | C152: 10 | D152: 0 | E152: =GETPIVOTDATA("Sum of High Discount Flag",$A$107,"Region","Asia","Salesperson","M. Rossi")/GETPIVOTDATA("Total Orders",$A$107,"Region","Asia","Salesperson","M. Rossi") -> 0
B153: N. Brown | C153: 10 | D153: 1 | E153: =GETPIVOTDATA("Sum of High Discount Flag",$A$107,"Region","Asia","Salesperson","N. Brown")/GETPIVOTDATA("Total Orders",$A$107,"Region","Asia","Salesperson","N. Brown") -> 0.1
B154: O. Wang | C154: 8 | D154: 4 | E154: =GETPIVOTDATA("Sum of High Discount Flag",$A$107,"Region","Asia","Salesperson","O. Wang")/GETPIVOTDATA("Total Orders",$A$107,"Region","Asia","Salesperson","O. Wang") -> 0.5
B155: Unassigned | C155: 2 | D155: 0 | E155: =GETPIVOTDATA("Sum of High Discount Flag",$A$107,"Region","Asia","Salesperson","Unassigned")/GETPIVOTDATA("Total Orders",$A$107,"Region","Asia","Salesperson","Unassigned") -> 0
A156: Europe | B156: A. Patel | C156: 10 | D156: 1 | E156: =GETPIVOTDATA("Sum of High Discount Flag",$A$107,"Region","Europe","Salesperson","A. Patel")/GETPIVOTDATA("Total Orders",$A$107,"Region","Europe","Salesperson","A. Patel") -> 0.1
B157: B. Chen | C157: 15 | D157: 2 | E157: =GETPIVOTDATA("Sum of High Discount Flag",$A$107,"Region","Europe","Salesperson","B. Chen")/GETPIVOTDATA("Total Orders",$A$107,"Region","Europe","Salesperson","B. Chen") -> 0.13333333
B158: C. Otieno | C158: 5 | D158: 1 | E158: =GETPIVOTDATA("Sum of High Discount Flag",$A$107,"Region","Europe","Salesperson","C. Otieno")/GETPIVOTDATA("Total Orders",$A$107,"Region","Europe","Salesperson","C. Otieno") -> 0.2
B159: D. Smith | C159: 11 | D159: 1 | E159: =GETPIVOTDATA("Sum of High Discount Flag",$A$107,"Region","Europe","Salesperson","D. Smith")/GETPIVOTDATA("Total Orders",$A$107,"Region","Europe","Salesperson","D. Smith") -> 0.090909091
B160: E. Garcia | C160: 16 | D160: 2 | E160: =GETPIVOTDATA("Sum of High Discount Flag",$A$107,"Region","Europe","Salesperson","E. Garcia")/GETPIVOTDATA("Total Orders",$A$107,"Region","Europe","Salesperson","E. Garcia") -> 0.125
B161: F. Müller | C161: 11 | D161: 0 | E161: =GETPIVOTDATA("Sum of High Discount Flag",$A$107,"Region","Europe","Salesperson","F. Müller")/GETPIVOTDATA("Total Orders",$A$107,"Region","Europe","Salesperson","F. Müller") -> 0
...

Sheet Dashboard
F26: =GETPIVOTDATA("GrossRevenue",'Pivot 1'!$D$2) -> 10919009 | H26: =Pivot!E60 -> 17304.293 | J26: =Pivot!E66 -> 0.31347291
F28: =GETPIVOTDATA("Sum of GrossProfit",Pivot!$A$63) -> 3422813.4 | H28: =GETPIVOTDATA("OnTime",Pivot!$A$70) -> 0.2725832
